[
  {
    "about": "About:        see more",
    "company": "Heinen's Grocery Store",
    "jobTitle": "2 years 11 months in role                    4 years 11 months in company",
    "leadPanel": "/sales/lead/ACwAACbqYQsBJEJtMtYsA3_ZycVo77b4ZjmXVvw,NAME_SEARCH,1mcd?_ntb=%2Fb3tu0iwTKeaQVASZGH%2F8w%3D%3D",
    "location": "Cleveland, Ohio, United States",
    "name": "Cory Walker",
    "photo": "https://media.licdn.com/dms/image/D4E03AQHU4FBqf2LMWw/profile-displayphoto-shrink_100_100/0/1682098452956?e=1714608000&v=beta&t=KFDwpxEsZxnnPaAIpb2UaVNHtWTDaaXazz5RMjsPmLM",
    "title": "Warehouse Buyer"
  },
  {
    "about": "About:        see more",
    "company": "Rural King",
    "jobTitle": "2 months in role                    1 year 10 months in company",
    "leadPanel": "/sales/lead/ACwAAB8vYoEBRY_kMUhre8dt57x8M9ywRMvbTY0,NAME_SEARCH,UWCY?_ntb=%2Fb3tu0iwTKeaQVASZGH%2F8w%3D%3D",
    "location": "Greenup, Illinois, United States",
    "name": "Seth Repp",
    "photo": null,
    "title": "Buyer"
  },
  {
    "about": "",
    "company": "Whole Foods Market",
    "jobTitle": "28 years 10 months in role                    28 years 10 months in company",
    "leadPanel": "/sales/lead/ACwAAAMWJ8cBFNByAeVOG5nYyZS6-kN7zAhQACo,NAME_SEARCH,vffQ?_ntb=%2Fb3tu0iwTKeaQVASZGH%2F8w%3D%3D",
    "location": "Wadsworth, Illinois, United States",
    "name": "Thomas Williamson",
    "photo": "https://media.licdn.com/dms/image/C4E03AQH_znA1a1i-LQ/profile-displayphoto-shrink_100_100/0/1525374398109?e=1714608000&v=beta&t=NTlopaj5tT9PKfSTjtOl3XLxMAY587vUBjMBltQz-yI",
    "title": "Buyer"
  },
  {
    "about": "About:        see more",
    "company": "Lowe's Companies, Inc.",
    "jobTitle": "2 years 6 months in role                    4 years 1 month in company",
    "leadPanel": "/sales/lead/ACwAAA9oZqIB_H9WPPFRwviZkyC-RSsrtJ3bBio,NAME_SEARCH,6LQx?_ntb=%2Fb3tu0iwTKeaQVASZGH%2F8w%3D%3D",
    "location": "Upland, California, United States",
    "name": "Michael James",
    "photo": null,
    "title": "Buyer"
  },
  {
    "about": "About:        see more",
    "company": "The Exchange",
    "jobTitle": "5 years 4 months in role                    5 years 4 months in company",
    "leadPanel": "/sales/lead/ACwAAADJuHIBbv1gVq0FJlxv-DxqIi9rT4aqtJU,NAME_SEARCH,PyrF?_ntb=%2Fb3tu0iwTKeaQVASZGH%2F8w%3D%3D",
    "location": "New York, New York, United States",
    "name": "Richard Reiss",
    "photo": "https://media.licdn.com/dms/image/D4E03AQGRw1WSLEHheQ/profile-displayphoto-shrink_100_100/0/1686776581601?e=1714608000&v=beta&t=YBt9m9UgrPt6eK7OepVpTv1I4FiqLIrucauJgB2cHxc",
    "title": "Buyer"
  },
  {
    "about": "About:        see more",
    "company": "Value Merchandise, International",
    "jobTitle": "2 years 7 months in role                    2 years 7 months in company",
    "leadPanel": "/sales/lead/ACwAAADFBBkBNAfpo9Jo1hQjNvvL9pkUfqoNjRM,NAME_SEARCH,36c2?_ntb=%2Fb3tu0iwTKeaQVASZGH%2F8w%3D%3D",
    "location": "Huntersville, North Carolina, United States",
    "name": "Laura Meyer",
    "photo": null,
    "title": "Buyer"
  },
  {
    "about": "About:        see more",
    "company": "PetSmart",
    "jobTitle": "7 months in role                    4 years 7 months in company",
    "leadPanel": "/sales/lead/ACwAABGuq-cBjTm5XEqL_e2QLmmpGhINjN5G88U,NAME_SEARCH,LJUc?_ntb=%2Fb3tu0iwTKeaQVASZGH%2F8w%3D%3D",
    "location": "Dallas, Texas, United States",
    "name": "Katharine Kirby",
    "photo": "data:image/gif;base64,R0lGODlhAQABAIAAAAAAAP///yH5BAEAAAAALAAAAAABAAEAAAIBRAA7",
    "title": "Buyer II"
  },
  {
    "about": "About:        see more",
    "company": "myAgway",
    "jobTitle": "5 years  in role                    5 years  in company",
    "leadPanel": "/sales/lead/ACwAAAEiOVQB12_Nm6PyDyOpyi_g04fTchT63rc,NAME_SEARCH,ece4?_ntb=%2Fb3tu0iwTKeaQVASZGH%2F8w%3D%3D",
    "location": "Minneapolis, Minnesota, United States",
    "name": "Tonya Carroll",
    "photo": null,
    "title": "Buyer"
  },
  {
    "about": "About:        see more",
    "company": "",
    "jobTitle": "1 year 5 months in role                    1 year 5 months in company",
    "leadPanel": "/sales/lead/ACwAABU9WVIBFSAbDxhTtbEkEmYMDnPdVLAH0fY,NAME_SEARCH,gM65?_ntb=%2Fb3tu0iwTKeaQVASZGH%2F8w%3D%3D",
    "location": "Minneapolis, Minnesota, United States",
    "name": "Loic Attikossie",
    "photo": "https://media.licdn.com/dms/image/D5603AQGznVNxyU0AbA/profile-displayphoto-shrink_100_100/0/1680048774989?e=1714608000&v=beta&t=4XtoMf9ssGFkQtJ3P4_oANM76WW2t_DVU-yRIbolNTU",
    "title": "Buyer - Cat Value"
  },
  {
    "about": "About:        see more",
    "company": "",
    "jobTitle": "11 years 3 months in role                    11 years 3 months in company",
    "leadPanel": "/sales/lead/ACwAAA5JBG8B0IiCjei5FP--Xcsr2q2qQmoGarQ,NAME_SEARCH,jIJr?_ntb=%2Fb3tu0iwTKeaQVASZGH%2F8w%3D%3D",
    "location": "North Branford, Connecticut, United States",
    "name": "Ryan Dowson",
    "photo": null,
    "title": "Buyer"
  },
  {
    "about": "About:        see more",
    "company": "BEALLS OUTLET",
    "jobTitle": "1 year 4 months in role                    1 year 4 months in company",
    "leadPanel": "/sales/lead/ACwAAAFv4J0BG06me1RBw3l6EfvutAh0ZKwl6rY,NAME_SEARCH,hF-1?_ntb=%2Fb3tu0iwTKeaQVASZGH%2F8w%3D%3D",
    "location": "New York, New York, United States",
    "name": "Suzanne Paterno",
    "photo": "https://media.licdn.com/dms/image/D4E03AQHU4FBqf2LMWw/profile-displayphoto-shrink_100_100/0/1682098452956?e=1714608000&v=beta&t=KFDwpxEsZxnnPaAIpb2UaVNHtWTDaaXazz5RMjsPmLM",
    "title": "NY Market Buyer"
  },
  {
    "about": "",
    "company": "Avalon Flooring",
    "jobTitle": "2 years 1 month in role                    4 years 6 months in company",
    "leadPanel": "/sales/lead/ACwAAA76GScBR2KZ4uvKZhP-ZtxERFdeoEC14TE,NAME_SEARCH,uQCj?_ntb=%2Fb3tu0iwTKeaQVASZGH%2F8w%3D%3D",
    "location": "Marlton, New Jersey, United States",
    "name": "Marc Martorano",
    "photo": null,
    "title": "Buyer Hardwood and Vinyl"
  },
  {
    "about": "",
    "company": "Long's Jewelers",
    "jobTitle": "1 year 5 months in role                    1 year 5 months in company",
    "leadPanel": "/sales/lead/ACwAACLLix0BlLnt0Yge5izaVNYh_gDbll7xgqA,NAME_SEARCH,8dU8?_ntb=%2Fb3tu0iwTKeaQVASZGH%2F8w%3D%3D",
    "location": "United States",
    "name": "James Hudson",
    "photo": "https://media.licdn.com/dms/image/D4E03AQE1PHHvaNlFCA/profile-displayphoto-shrink_100_100/0/1696110431722?e=1714608000&v=beta&t=gTShUCtyyjHfgQ8p0pNf61BJZidbHRkJdTuKGTYES74",
    "title": "Buyer for Fine Watches"
  },
  {
    "about": "",
    "company": "Backcountry",
    "jobTitle": "3 months in role                    7 years 8 months in company",
    "leadPanel": "/sales/lead/ACwAAAzX73YB3noUw04TXVhJYDAtCgnWju8_KyE,NAME_SEARCH,Mjdi?_ntb=%2Fb3tu0iwTKeaQVASZGH%2F8w%3D%3D",
    "location": "Salt Lake City, Utah, United States",
    "name": "James Griffin",
    "photo": null,
    "title": "Buyer"
  },
  {
    "about": "",
    "company": "GivemetheVin.com",
    "jobTitle": "1 year 11 months in role                    1 year 11 months in company",
    "leadPanel": "/sales/lead/ACwAABV7eooBZilzHb5ZIa8FoytSQWqbRQEkA0Y,NAME_SEARCH,KrMI?_ntb=%2Fb3tu0iwTKeaQVASZGH%2F8w%3D%3D",
    "location": "Fort Worth, Texas, United States",
    "name": "Roy Russ",
    "photo": "https://media.licdn.com/dms/image/C5603AQFBm8rua_dIUw/profile-displayphoto-shrink_200_200/0/1517493426963?e=1714608000&v=beta&t=5n8DdYUo6dochaIepAeqaoE-M7iS6ejYd7MtLMhg9VQ",
    "title": "Buyer"
  },
  {
    "about": "About:        see more",
    "company": "Nordstrom",
    "jobTitle": "3 years 3 months in role                    3 years 3 months in company",
    "leadPanel": "/sales/lead/ACwAAANyvQcBOmcQwkW90i19ASkwRKG6HwT_1aQ,NAME_SEARCH,0aGH?_ntb=%2Fb3tu0iwTKeaQVASZGH%2F8w%3D%3D",
    "location": "Miami, Florida, United States",
    "name": "LAURA KEIGHLEY",
    "photo": null,
    "title": "Buyer Home & Lifestyle"
  },
  {
    "about": "",
    "company": "Starbucks",
    "jobTitle": "2 years 11 months in role                    6 years 3 months in company",
    "leadPanel": "/sales/lead/ACwAABQ5NowBqhzaFmClLOqqY01kQnT0fzMH5sk,NAME_SEARCH,ekJd?_ntb=%2Fb3tu0iwTKeaQVASZGH%2F8w%3D%3D",
    "location": "Aiken, South Carolina, United States",
    "name": "Christy Boyd",
    "photo": "https://media.licdn.com/dms/image/D4E03AQEmgPUtBKey2w/profile-displayphoto-shrink_100_100/0/1677356153254?e=1714608000&v=beta&t=dKEOyzzEyYN_7sjpIbYsQxa8kfECfQiUfpr7_iCgPgM",
    "title": "Maintenance Buyer Services"
  },
  {
    "about": "",
    "company": "Amcor",
    "jobTitle": "5 years  in role                    5 years  in company",
    "leadPanel": "/sales/lead/ACwAABrQhf8Bgk3quB2APs-tBa6OCQSRy8NoniU,NAME_SEARCH,rzZM?_ntb=%2Fb3tu0iwTKeaQVASZGH%2F8w%3D%3D",
    "location": "Greater Boston",
    "name": "Joseph Dalabon",
    "photo": null,
    "title": "Purchaser"
  },
  {
    "about": "",
    "company": "Pack Rat Outdoor Center",
    "jobTitle": "2 years 1 month in role                    2 years 1 month in company",
    "leadPanel": "/sales/lead/ACwAABfhFB8BULarRNhjBnrIAiSiLyLMnE9XDsk,OUT_OF_NETWORK,nojq?_ntb=%2Fb3tu0iwTKeaQVASZGH%2F8w%3D%3D",
    "location": "Greater Philadelphia",
    "name": "RYAN BRADWAY",
    "photo": "https://media.licdn.com/dms/image/C5103AQFK2JNhe32Ttw/profile-displayphoto-shrink_100_100/0/1517537923198?e=1714608000&v=beta&t=o41CUaivCrSZgro03N8Twl5aOWS_nP9APZmXmp0UkNI",
    "title": "Buyer"
  },
  {
    "about": "About:        see more",
    "company": "",
    "jobTitle": "24 years 8 months in role                    24 years 8 months in company",
    "leadPanel": "/sales/lead/ACwAAAhgA1gBNNrFj1lqCdKSV6mjVFyWmcq-MoA,NAME_SEARCH,rsis?_ntb=%2Fb3tu0iwTKeaQVASZGH%2F8w%3D%3D",
    "location": "Fayetteville, Arkansas, United States",
    "name": "Rick Spicer",
    "photo": null,
    "title": "Equipment Buyer/part owner"
  },
  {
    "about": "",
    "company": "DICK'S Sporting Goods",
    "jobTitle": "2 months in role                    4 years 11 months in company",
    "leadPanel": "/sales/lead/ACwAAAF_QKUBJUHq80_Fw3Of7-MByt5nh-F25nY,NAME_SEARCH,Er8-?_ntb=%2Fb3tu0iwTKeaQVASZGH%2F8w%3D%3D",
    "location": "Pittsburgh, Pennsylvania, United States",
    "name": "Ryan Meyer",
    "photo": "https://media.licdn.com/dms/image/D4E03AQHU4FBqf2LMWw/profile-displayphoto-shrink_100_100/0/1682098452956?e=1714608000&v=beta&t=KFDwpxEsZxnnPaAIpb2UaVNHtWTDaaXazz5RMjsPmLM",
    "title": "Buyer, NHL and Hyperlocal"
  },
  {
    "about": "",
    "company": "CIRCA",
    "jobTitle": "1 year  in role                    1 year  in company",
    "leadPanel": "/sales/lead/ACwAAAXExTkBPk9mzeOhITxo8wbTqUQ0DRMRTBE,NAME_SEARCH,_89Y?_ntb=%2Fb3tu0iwTKeaQVASZGH%2F8w%3D%3D",
    "location": "New York, New York, United States",
    "name": "Kimberly Martinez, G.G.",
    "photo": null,
    "title": "Buyer"
  },
  {
    "about": "About:        see more",
    "company": "McGuckin Hardware",
    "jobTitle": "8 months in role                    3 years  in company",
    "leadPanel": "/sales/lead/ACwAAAQAnsoBxDU-H7xmjh7IkabNid_bLf3C5AM,NAME_SEARCH,3-4D?_ntb=%2Fb3tu0iwTKeaQVASZGH%2F8w%3D%3D",
    "location": "Denver, Colorado, United States",
    "name": "Kristen Busch",
    "photo": "https://media.licdn.com/dms/image/C4E03AQGYNyuL8HSRBQ/profile-displayphoto-shrink_100_100/0/1517720831009?e=1714608000&v=beta&t=Q71hWOs9pDOblX1e6aSEK2yVslFC5hoHqlaiMf1qtLU",
    "title": "Buyer"
  },
  {
    "about": "About:        see more",
    "company": "Acme Tools",
    "jobTitle": "5 years 6 months in role                    5 years 6 months in company",
    "leadPanel": "/sales/lead/ACwAAAtDnOEB3SVqOo0kvR9kj0KGwnEXTOQ7G_U,NAME_SEARCH,aX-Q?_ntb=%2Fb3tu0iwTKeaQVASZGH%2F8w%3D%3D",
    "location": "Grand Forks, North Dakota, United States",
    "name": "Wes Arthur",
    "photo": null,
    "title": "Buyer"
  },
  {
    "about": "About:        see more",
    "company": "Marshall Retail Group/InMotion",
    "jobTitle": "2 years 10 months in role                    4 years 4 months in company",
    "leadPanel": "/sales/lead/ACwAAB6SaZ0BW27DzCTAU6LeDIqRIgdD0dpuB3Y,NAME_SEARCH,OJsH?_ntb=%2Fb3tu0iwTKeaQVASZGH%2F8w%3D%3D",
    "location": "Las Vegas, Nevada, United States",
    "name": "Lindsey Eaton",
    "photo": "https://media.licdn.com/dms/image/D4E03AQE8Bh4tYLsLTw/profile-displayphoto-shrink_100_100/0/1675712519801?e=1714608000&v=beta&t=TwTk4B6RtkKKL2x8n0Y7-QzI_ooV6HGe_YtzdqDZm9I",
    "title": "Buyer"
  },
  {
    "about": "About:        see more",
    "company": "Lyon Workspace Products",
    "jobTitle": "1 year 8 months in role                    1 year 8 months in company",
    "leadPanel": "/sales/lead/ACwAABCCSxoB6g0Bt1HHyORjhr-TdwXBkcCW2KI,NAME_SEARCH,0TQE?_ntb=%2Fb3tu0iwTKeaQVASZGH%2F8w%3D%3D",
    "location": "Anderson, South Carolina, United States",
    "name": "Danny Myers",
    "photo": null,
    "title": "Buyer"
  },
  {
    "about": "",
    "company": "Ross Stores, Inc.",
    "jobTitle": "in role                      in company",
    "leadPanel": "/sales/lead/ACwAAA05ZmIB8wPpi9KyflGcQ41saOGjvQqLc4A,OUT_OF_NETWORK,5CSA?_ntb=%2Fb3tu0iwTKeaQVASZGH%2F8w%3D%3D",
    "location": "Roselle, Illinois, United States",
    "name": "Jim Welgos",
    "photo": "https://media.licdn.com/dms/image/D5603AQG6sNQbwjkyCQ/profile-displayphoto-shrink_100_100/0/1688994053897?e=1714608000&v=beta&t=RyEVg-22pPXjFv9NIpcf3zUc9bNlkixG89o0A97giVw",
    "title": "Buyer"
  },
  {
    "about": "",
    "company": "Max Mara Fashion Group",
    "jobTitle": "2 months in role                    5 years 10 months in company",
    "leadPanel": "/sales/lead/ACwAABcx0w4Boy61LaByOYva4m7Hgo2n-xDCag8,NAME_SEARCH,N6JF?_ntb=%2Fb3tu0iwTKeaQVASZGH%2F8w%3D%3D",
    "location": "New York, New York, United States",
    "name": "Sophia Poster",
    "photo": null,
    "title": "Buyer"
  },
  {
    "about": "About:        see more",
    "company": "Meijer",
    "jobTitle": "5 months in role                    11 years 9 months in company",
    "leadPanel": "/sales/lead/ACwAAAWXGhkBA6QfE1cgQRlRhnXAJesY5jTiU2c,NAME_SEARCH,oi-n?_ntb=%2Fb3tu0iwTKeaQVASZGH%2F8w%3D%3D",
    "location": "New York, New York, United States",
    "name": "Kendal Parker",
    "photo": "https://media.licdn.com/dms/image/D5603AQGkvXUK2Pwx0Q/profile-displayphoto-shrink_100_100/0/1706237616482?e=1714608000&v=beta&t=uBaeIIqK1o7AiQxKiNFxFov17VqeLBLcjwN2t9DCNXw",
    "title": "Omni Channel Buyer"
  },
  {
    "about": "About:        see more",
    "company": "",
    "jobTitle": "4 years 6 months in role                    4 years 6 months in company",
    "leadPanel": "/sales/lead/ACwAAAIH380BXMEVUGOwr6axAdlJrSq-_lDQO2U,NAME_SEARCH,KQW4?_ntb=%2Fb3tu0iwTKeaQVASZGH%2F8w%3D%3D",
    "location": "Grand Rapids Metropolitan Area",
    "name": "Christine Miskowski",
    "photo": null,
    "title": "Buyer - Own Brand/Private Label - Ophelia Roe, Tranquil & True & Womens Sleepwear"
  },
  {
    "about": "",
    "company": "Tractor Supply Company",
    "jobTitle": "2 months in role                    13 years  in company",
    "leadPanel": "/sales/lead/ACwAABi3NfQBf8hHyOwUTn8xvg26exf4jofFcb8,NAME_SEARCH,ABdg?_ntb=%2Fb3tu0iwTKeaQVASZGH%2F8w%3D%3D",
    "location": "Brentwood, Tennessee, United States",
    "name": "Jeremy Rea",
    "photo": "https://media.licdn.com/dms/image/D4E03AQHU4FBqf2LMWw/profile-displayphoto-shrink_100_100/0/1682098452956?e=1714608000&v=beta&t=KFDwpxEsZxnnPaAIpb2UaVNHtWTDaaXazz5RMjsPmLM",
    "title": "Buyer II"
  },
  {
    "about": "",
    "company": "Landry's",
    "jobTitle": "8 months in role                    2 years 10 months in company",
    "leadPanel": "/sales/lead/ACwAACD6JzgBDh1d5eGghqgnAzjGNGhPdqkXh18,NAME_SEARCH,a6TW?_ntb=%2Fb3tu0iwTKeaQVASZGH%2F8w%3D%3D",
    "location": "Greater Houston",
    "name": "Madeline Lim",
    "photo": null,
    "title": "Buyer"
  },
  {
    "about": "About:        see more",
    "company": "Century 21 Stores",
    "jobTitle": "1 year 8 months in role                    1 year 8 months in company",
    "leadPanel": "/sales/lead/ACwAABaumyUBK1izPIrBRZwKcT5DGtUAEk72G3U,NAME_SEARCH,Q6ft?_ntb=%2Fb3tu0iwTKeaQVASZGH%2F8w%3D%3D",
    "location": "New York City Metropolitan Area",
    "name": "Stacy DeFeo",
    "photo": "https://media.licdn.com/dms/image/C5603AQEmR237DazXQg/profile-displayphoto-shrink_100_100/0/1550761168601?e=1714608000&v=beta&t=1LOlAJdKcqjLpQhPp_ZHNvtu11ZxiPWwF2LCvcUomrU",
    "title": "Buyer"
  },
  {
    "about": "About:        see more",
    "company": "Delta Galil Industries",
    "jobTitle": "3 months in role                     3 months in company",
    "leadPanel": "/sales/lead/ACwAAAIIDw4BfX9Jp0DAKv4_TP_-897CXXeMyNs,NAME_SEARCH,hxyF?_ntb=%2Fb3tu0iwTKeaQVASZGH%2F8w%3D%3D",
    "location": "New York City Metropolitan Area",
    "name": "Laura Poe",
    "photo": null,
    "title": "Buyer and Site Merchandiser, Florence by Mills"
  },
  {
    "about": "About:        see more",
    "company": "Nordstrom",
    "jobTitle": "1 year 2 months in role                    6 years 2 months in company",
    "leadPanel": "/sales/lead/ACwAAAOJMDABnV9DQ8caW5jSGSikVlc8xQ5fjuE,NAME_SEARCH,kaXG?_ntb=%2Fb3tu0iwTKeaQVASZGH%2F8w%3D%3D",
    "location": "Seattle, Washington, United States",
    "name": "Molly M.",
    "photo": "https://media.licdn.com/dms/image/C5603AQFWudrS8kAGWg/profile-displayphoto-shrink_100_100/0/1657491732770?e=1714608000&v=beta&t=bU7T5wB2tbVS_urMfuVbI4LetVsoYKFIb9yf18kFUqA",
    "title": "Buyer-Fine Jewelry"
  },
  {
    "about": "About:        see more",
    "company": "General RV Center",
    "jobTitle": "1 year 2 months in role                    3 years 4 months in company",
    "leadPanel": "/sales/lead/ACwAAAwa4-0Bb6re1Okwlf21kCiMKEzDwbIr6Fo,NAME_SEARCH,35Th?_ntb=%2Fb3tu0iwTKeaQVASZGH%2F8w%3D%3D",
    "location": "Northville, Michigan, United States",
    "name": "Odria Lin",
    "photo": null,
    "title": "Buyer"
  },
  {
    "about": "About:        see more",
    "company": "Carl Meyers",
    "jobTitle": "4 months in role                     4 months in company",
    "leadPanel": "/sales/lead/ACwAAATHDaEBqr7qSxcApYw_TC_jj5EEWghQl8U,NAME_SEARCH,HHHK?_ntb=%2Fb3tu0iwTKeaQVASZGH%2F8w%3D%3D",
    "location": "Greater Lexington Area",
    "name": "Haley Harris Gatewood",
    "photo": "https://media.licdn.com/dms/image/C4D03AQG6PqbuRZpmtA/profile-displayphoto-shrink_100_100/0/1609296775343?e=1714608000&v=beta&t=nR-yHbykrCoTdcXDFwjollZWD8TlgiXE5pdRkb0thfo",
    "title": "Sales & Buyer"
  },
  {
    "about": "About:        see more",
    "company": "Whole Foods Market",
    "jobTitle": "5 years 9 months in role                    5 years 9 months in company",
    "leadPanel": "/sales/lead/ACwAADOX7A4B5SWyoAFpDoMz4l-GeD9Vikxu4ss,NAME_SEARCH,fxsK?_ntb=%2Fb3tu0iwTKeaQVASZGH%2F8w%3D%3D",
    "location": "Los Angeles, California, United States",
    "name": "Anastasia Hollande",
    "photo": null,
    "title": "Whole Body Buyer"
  },
  {
    "about": "",
    "company": "Saks OFF 5TH",
    "jobTitle": "3 years 2 months in role                    6 years 2 months in company",
    "leadPanel": "/sales/lead/ACwAAAibcQwBym99ELSvFsEXLqTf4eiWsOJuAMw,NAME_SEARCH,f72_?_ntb=%2Fb3tu0iwTKeaQVASZGH%2F8w%3D%3D",
    "location": "New York, New York, United States",
    "name": "Amy Giedl",
    "photo": "https://media.licdn.com/dms/image/C4E03AQHo_5C53n-qhQ/profile-displayphoto-shrink_100_100/0/1667916275880?e=1714608000&v=beta&t=CsMG3xgR9KVR3I70MQRvwu3CYHBt0aCoDcy7UZgqN3w",
    "title": "Omni Buyer - Womens Denim, Outerwear & Swim"
  },
  {
    "about": "",
    "company": "The TJX Companies, Inc.",
    "jobTitle": "1 year 11 months in role                    1 year 11 months in company",
    "leadPanel": "/sales/lead/ACwAAAzargsBfOarpn9bHKn_3t_q0lO4j-_48F0,NAME_SEARCH,NIWh?_ntb=%2Fb3tu0iwTKeaQVASZGH%2F8w%3D%3D",
    "location": "Long Beach, California, United States",
    "name": "Eric Trout",
    "photo": null,
    "title": "Buyer"
  },
  {
    "about": "About:        see more",
    "company": "Associated Wholesale Grocers",
    "jobTitle": "1 year 7 months in role                    1 year 7 months in company",
    "leadPanel": "/sales/lead/ACwAABUbAuABWA39YfB4UkgEvSC9XJIKT6Bnzak,NAME_SEARCH,vggu?_ntb=%2Fb3tu0iwTKeaQVASZGH%2F8w%3D%3D",
    "location": "Greater Minneapolis-St. Paul Area",
    "name": "David Beck",
    "photo": "https://media.licdn.com/dms/image/D4E03AQHU4FBqf2LMWw/profile-displayphoto-shrink_100_100/0/1682098452956?e=1714608000&v=beta&t=KFDwpxEsZxnnPaAIpb2UaVNHtWTDaaXazz5RMjsPmLM",
    "title": "Produce buyer"
  },
  {
    "about": "",
    "company": "UNFI",
    "jobTitle": "2 years 7 months in role                    2 years 7 months in company",
    "leadPanel": "/sales/lead/ACwAAARXIvAB-7ebdEgYmSmt9_ulCEE4_FBBCRs,OUT_OF_NETWORK,3HMV?_ntb=%2Fb3tu0iwTKeaQVASZGH%2F8w%3D%3D",
    "location": "Eden Prairie, Minnesota, United States",
    "name": "Billy Hagert",
    "photo": null,
    "title": "Fresh Buyer"
  },
  {
    "about": "About:        see more",
    "company": "Calbag Metals",
    "jobTitle": "10 months in role                     10 months in company",
    "leadPanel": "/sales/lead/ACwAABmtgQwBLNdx9ahN0LvWYOG0h0LmSdJX2WM,NAME_SEARCH,nb21?_ntb=%2Fb3tu0iwTKeaQVASZGH%2F8w%3D%3D",
    "location": "Portland, Oregon Metropolitan Area",
    "name": "Jaime Catota",
    "photo": "https://media.licdn.com/dms/image/D5603AQEHK3epSaf1NQ/profile-displayphoto-shrink_100_100/0/1665848645992?e=1714608000&v=beta&t=9JH-YgkqVGBFBCmJB-j212MoWkl2c_s_b8A93FCvZSI",
    "title": "Buyer"
  },
  {
    "about": "",
    "company": "Maisonette",
    "jobTitle": "1 year 9 months in role                    1 year 9 months in company",
    "leadPanel": "/sales/lead/ACwAAAGdEi4BqEt8O-bX_-hs4tWsWy0yZz6yiNA,NAME_SEARCH,z23w?_ntb=%2Fb3tu0iwTKeaQVASZGH%2F8w%3D%3D",
    "location": "Richland, Michigan, United States",
    "name": "Daniel W.",
    "photo": null,
    "title": "Buyer-Toys"
  },
  {
    "about": "About:        see more",
    "company": "SNIPES",
    "jobTitle": "5 years 9 months in role                    5 years 9 months in company",
    "leadPanel": "/sales/lead/ACwAAAm9GLABT41L0dKQBTIKQ3ZvrxXPaTRbQ_0,NAME_SEARCH,PjXM?_ntb=%2Fb3tu0iwTKeaQVASZGH%2F8w%3D%3D",
    "location": "Bronx, New York, United States",
    "name": "David Wingard",
    "photo": "data:image/gif;base64,R0lGODlhAQABAIAAAAAAAP///yH5BAEAAAAALAAAAAABAAEAAAIBRAA7",
    "title": "Manager | Buyer"
  },
  {
    "about": "About:        see more",
    "company": "Bealls, Inc.",
    "jobTitle": "3 years  in role                    3 years  in company",
    "leadPanel": "/sales/lead/ACwAAAYVqj8B4Yj_Nj0nbvYHbccuUdtxvA3LIHU,NAME_SEARCH,ExxC?_ntb=%2Fb3tu0iwTKeaQVASZGH%2F8w%3D%3D",
    "location": "United States",
    "name": "JaNaie Fort",
    "photo": null,
    "title": "Buyer - Women's & Kid's Apparel"
  },
  {
    "about": "About:        see more",
    "company": "Albertsons Companies",
    "jobTitle": "4 years 9 months in role                    5 years 9 months in company",
    "leadPanel": "/sales/lead/ACwAAATelgMBluKNQo20fgRUhow1-G_66A7PqV0,NAME_SEARCH,RYsh?_ntb=%2Fb3tu0iwTKeaQVASZGH%2F8w%3D%3D",
    "location": "Bradenton, Florida, United States",
    "name": "Heather Lans",
    "photo": "https://media.licdn.com/dms/image/D5603AQG5Fli0hfsOwA/profile-displayphoto-shrink_100_100/0/1699633736759?e=1714608000&v=beta&t=ZGD3g59V4_XSK3MfPREXBTGLSDs0Z94qCxdTqnB9aT8",
    "title": "Buyer"
  },
  {
    "about": "About:        see more",
    "company": "Read Between The Lines",
    "jobTitle": "5 years 6 months in role                    5 years 6 months in company",
    "leadPanel": "/sales/lead/ACwAAC4bzJ4BGn_q9OIiJNcpGGc_jcoPevZ-MuQ,OUT_OF_NETWORK,vUqU?_ntb=%2Fb3tu0iwTKeaQVASZGH%2F8w%3D%3D",
    "location": "Fort Worth, Texas, United States",
    "name": "Erick Martin",
    "photo": null,
    "title": "Produce Buyer"
  },
  {
    "about": "",
    "company": "Kinney Drugs",
    "jobTitle": "4 years 5 months in role                    7 years 3 months in company",
    "leadPanel": "/sales/lead/ACwAABVsmQ8BlmYsiusSj1JHAbn5oggqWh0NI64,NAME_SEARCH,Q63-?_ntb=%2Fb3tu0iwTKeaQVASZGH%2F8w%3D%3D",
    "location": "Dallas-Fort Worth Metroplex",
    "name": "Brady Littleton",
    "photo": "https://media.licdn.com/dms/image/C4E03AQHGMGI3WNIxFw/profile-displayphoto-shrink_100_100/0/1583261012650?e=1714608000&v=beta&t=P5-ehP0QXg7o86ylzxEp_QgLbV-V6b_WZ1-8_QNcQ-U",
    "title": "Buyer"
  },
  {
    "about": "",
    "company": "",
    "jobTitle": "5 months in role                    13 years 8 months in company",
    "leadPanel": "/sales/lead/ACwAABz0tawB88OnlhT2C7Xsv7KZmOHvgkUaEdg,NAME_SEARCH,6655?_ntb=%2Fb3tu0iwTKeaQVASZGH%2F8w%3D%3D",
    "location": "Liverpool, New York, United States",
    "name": "Connor Hanretty",
    "photo": null,
    "title": "Buyer Analyst"
  },
  {
    "about": "About:        see more",
    "company": "Sterling Jewelers",
    "jobTitle": "10 years 10 months in role                    16 years 7 months in company",
    "leadPanel": "/sales/lead/ACwAAAouBYEBAD7uNP-Mcn32-ta5orqxEt6lV3w,NAME_SEARCH,HG-g?_ntb=%2Fb3tu0iwTKeaQVASZGH%2F8w%3D%3D",
    "location": "Cleveland, Ohio, United States",
    "name": "Brittany Childerson",
    "photo": "https://media.licdn.com/dms/image/D4E03AQHU4FBqf2LMWw/profile-displayphoto-shrink_100_100/0/1682098452956?e=1714608000&v=beta&t=KFDwpxEsZxnnPaAIpb2UaVNHtWTDaaXazz5RMjsPmLM",
    "title": "Buyer"
  },
  {
    "about": "",
    "company": "The TJX Companies, Inc.",
    "jobTitle": "3 years  in role                    9 years 3 months in company",
    "leadPanel": "/sales/lead/ACwAABB7zU4B9CfpTKfsGuwpen-Bd_J339VycG4,NAME_SEARCH,xjqw?_ntb=%2Fb3tu0iwTKeaQVASZGH%2F8w%3D%3D",
    "location": "Framingham, Massachusetts, United States",
    "name": "Jacquelyn Snell",
    "photo": null,
    "title": "Buyer"
  },
  {
    "about": "",
    "company": "The TJX Companies, Inc.",
    "jobTitle": "2 years 10 months in role                    7 years 8 months in company",
    "leadPanel": "/sales/lead/ACwAAA3zWkYBoQdyeTkYQYpa5V8oyhFwWPtYPOY,NAME_SEARCH,NkCH?_ntb=%2Fb3tu0iwTKeaQVASZGH%2F8w%3D%3D",
    "location": "Greater Boston",
    "name": "Tyler Hogan, MBA",
    "photo": "https://media.licdn.com/dms/image/C5603AQG23nrBlBOdiw/profile-displayphoto-shrink_100_100/0/1605026945041?e=1714608000&v=beta&t=B1gBZ8Nx80TwJXPvCx3SlWGT2paVZUudQihLRgsOXjU",
    "title": "Buyer"
  },
  {
    "about": "About:        see more",
    "company": "Bealls, Inc.",
    "jobTitle": "5 years 7 months in role                    5 years 7 months in company",
    "leadPanel": "/sales/lead/ACwAAAFrBfkBV0PWd7SiD8gR24ZdhmPFChk-RVw,NAME_SEARCH,fDnq?_ntb=%2Fb3tu0iwTKeaQVASZGH%2F8w%3D%3D",
    "location": "North Port-Sarasota Area",
    "name": "Lisa Broadbent",
    "photo": null,
    "title": "Buyer"
  },
  {
    "about": "",
    "company": "Ross Stores, Inc.",
    "jobTitle": "8 years 8 months in role                    8 years 8 months in company",
    "leadPanel": "/sales/lead/ACwAAAFc_PABdMmGcR8pw_oUSE1Qh_0WZREch6g,NAME_SEARCH,TGG-?_ntb=%2Fb3tu0iwTKeaQVASZGH%2F8w%3D%3D",
    "location": "Columbus, Ohio, United States",
    "name": "Joe Williams",
    "photo": "data:image/gif;base64,R0lGODlhAQABAIAAAAAAAP///yH5BAEAAAAALAAAAAABAAEAAAIBRAA7",
    "title": "Buyer Mens and Boys"
  },
  {
    "about": "",
    "company": "Whole Foods Market",
    "jobTitle": "28 years 6 months in role                    28 years 6 months in company",
    "leadPanel": "/sales/lead/ACwAACVhaacBvkXZTyjjIiWWRjmF58yKXvYJdd0,NAME_SEARCH,zJ2X?_ntb=%2Fb3tu0iwTKeaQVASZGH%2F8w%3D%3D",
    "location": "Holbrook, Massachusetts, United States",
    "name": "brian levin",
    "photo": null,
    "title": "Buyer"
  },
  {
    "about": "About:        see more",
    "company": "Buffalo Exchange",
    "jobTitle": "6 years  in role                    6 years  in company",
    "leadPanel": "/sales/lead/ACwAABXLz9wBqDI0Kgmi9RZKHwzeaIsY_WLHTkQ,NAME_SEARCH,ErYc?_ntb=%2Fb3tu0iwTKeaQVASZGH%2F8w%3D%3D",
    "location": "Glen Allen, Virginia, United States",
    "name": "Brian Reynolds",
    "photo": "https://media.licdn.com/dms/image/D4E03AQG5OFpOoE2Chg/profile-displayphoto-shrink_100_100/0/1700505377069?e=1714608000&v=beta&t=RxmuwxZPvi_FFo_58BcrGLNMr1NwO7tBFxMjLOH7uTY",
    "title": "Buyer II / Bakery & Deli"
  },
  {
    "about": "About:        see more",
    "company": "Super King Markets",
    "jobTitle": "8 months in role                     8 months in company",
    "leadPanel": "/sales/lead/ACwAAClDXtkB5Ny-sYObRP4TBdCJhkroGLDe2Ro,NAME_SEARCH,tWzW?_ntb=%2Fb3tu0iwTKeaQVASZGH%2F8w%3D%3D",
    "location": "Greater Philadelphia",
    "name": "Jo Zera",
    "photo": null,
    "title": "Buyer"
  },
  {
    "about": "",
    "company": "PIRCH",
    "jobTitle": "4 years 11 months in role                    9 years 5 months in company",
    "leadPanel": "/sales/lead/ACwAADiGNsMBE5qlZc2-fZOYQ0n_uUXVcPuhSKg,NAME_SEARCH,8gfl?_ntb=%2Fb3tu0iwTKeaQVASZGH%2F8w%3D%3D",
    "location": "United States",
    "name": "Fridreek Neqadimos",
    "photo": "https://media.licdn.com/dms/image/D4E03AQEclh-zRQKeKQ/profile-displayphoto-shrink_100_100/0/1698528566779?e=1714608000&v=beta&t=_A8PBwzLkY5mYwNyZW-KNw6FMZHpgrDpM1I-poWY3KE",
    "title": "Produce Buyer"
  },
  {
    "about": "About:        see more",
    "company": "",
    "jobTitle": "1 year 10 months in role                    1 year 10 months in company",
    "leadPanel": "/sales/lead/ACwAAAMGByEBHjmn8EWbeEZw0TfHL3inZZ_zqjo,NAME_SEARCH,T0De?_ntb=%2Fb3tu0iwTKeaQVASZGH%2F8w%3D%3D",
    "location": "San Diego, California, United States",
    "name": "Nicole M.",
    "photo": null,
    "title": "Buyer"
  },
  {
    "about": "",
    "company": "Bloomingdale's",
    "jobTitle": "10 months in role                     10 months in company",
    "leadPanel": "/sales/lead/ACwAAC4OVS0BVm8O1X_PNPwKSMqFuejbADzrxQc,NAME_SEARCH,FR0C?_ntb=%2Fb3tu0iwTKeaQVASZGH%2F8w%3D%3D",
    "location": "New York City Metropolitan Area",
    "name": "Victoria Barrell",
    "photo": "https://media.licdn.com/dms/image/D4E03AQHU4FBqf2LMWw/profile-displayphoto-shrink_100_100/0/1682098452956?e=1714608000&v=beta&t=KFDwpxEsZxnnPaAIpb2UaVNHtWTDaaXazz5RMjsPmLM",
    "title": "LDP Buyer Trainee"
  },
  {
    "about": "About:        see more",
    "company": "The TJX Companies, Inc.",
    "jobTitle": "13 years 11 months in role                    13 years 11 months in company",
    "leadPanel": "/sales/lead/ACwAAAOA9jUBjBMK4dPWNJHjs6xXem24IcoDRYo,NAME_SEARCH,-R5E?_ntb=%2Fb3tu0iwTKeaQVASZGH%2F8w%3D%3D",
    "location": "New York City Metropolitan Area",
    "name": "Julie Adams",
    "photo": null,
    "title": "Buyer - TJX Europe Beauty"
  },
  {
    "about": "",
    "company": "Ross Stores, Inc.",
    "jobTitle": "1 year  in role                    4 years 6 months in company",
    "leadPanel": "/sales/lead/ACwAAADjjk0BzoRDaAnGaWPNgJ3E9BlQhTvjbwA,NAME_SEARCH,R_Hs?_ntb=%2Fb3tu0iwTKeaQVASZGH%2F8w%3D%3D",
    "location": "New York City Metropolitan Area",
    "name": "Liz Csordas",
    "photo": "https://media.licdn.com/dms/image/D4E03AQEnVXohwXnKpg/profile-displayphoto-shrink_100_100/0/1686546199621?e=1714608000&v=beta&t=neaF_edsEy716nx13qy-hCUYgZYG7ykT5G4BbmHW2aU",
    "title": "Buyer - Mens Contemporary"
  },
  {
    "about": "",
    "company": "The TJX Companies, Inc.",
    "jobTitle": "1 year 4 months in role                    7 years 8 months in company",
    "leadPanel": "/sales/lead/ACwAAAfhWyMB5xvj67e9TNlT08pSFU05vJANmwI,NAME_SEARCH,DFPS?_ntb=%2Fb3tu0iwTKeaQVASZGH%2F8w%3D%3D",
    "location": "Greater Boston",
    "name": "Jessica Adam",
    "photo": null,
    "title": "Buyer - Beauty"
  },
  {
    "about": "",
    "company": "The TJX Companies, Inc.",
    "jobTitle": "1 year 8 months in role                    8 years 8 months in company",
    "leadPanel": "/sales/lead/ACwAABMdCcwBz3PZmJZIAc6tWopHTVrLBai9Tgk,NAME_SEARCH,-BmP?_ntb=%2Fb3tu0iwTKeaQVASZGH%2F8w%3D%3D",
    "location": "Needham, Massachusetts, United States",
    "name": "Joanna Murphy",
    "photo": "https://media.licdn.com/dms/image/C4D03AQEanTLtvIlicg/profile-displayphoto-shrink_100_100/0/1642193080742?e=1714608000&v=beta&t=0cwh8QyPNu6l4FF1j6fj6ibmkTEppjwBcWd2H9Yt24c",
    "title": "Buyer"
  },
  {
    "about": "",
    "company": "Rural King Farm & Home Store",
    "jobTitle": "2 years  in role                    2 years  in company",
    "leadPanel": "/sales/lead/ACwAABFPS7MByZNKQVph5J-vWtcBV2-J0TwxeWM,NAME_SEARCH,gIsT?_ntb=%2Fb3tu0iwTKeaQVASZGH%2F8w%3D%3D",
    "location": "Toledo, Illinois, United States",
    "name": "Tyler Creasey",
    "photo": null,
    "title": "Buyer"
  },
  {
    "about": "",
    "company": "TK MAXX",
    "jobTitle": "5 years 5 months in role                    10 years 9 months in company",
    "leadPanel": "/sales/lead/ACwAAAFCZp0BUEdTjspincFMSy7MXnrtbuEBaCU,NAME_SEARCH,SgPL?_ntb=%2Fb3tu0iwTKeaQVASZGH%2F8w%3D%3D",
    "location": "New York, New York, United States",
    "name": "Ashley Boynton",
    "photo": "https://media.licdn.com/dms/image/C4E03AQG74S4O57F8Cw/profile-displayphoto-shrink_100_100/0/1517722435605?e=1714608000&v=beta&t=uEF9hw84MdFRQVShUO4cyUPDnDF4nxX1bSc5S0rgAxg",
    "title": "Buyer - Pet"
  },
  {
    "about": "About:        see more",
    "company": "Variety Wholesalers, Inc",
    "jobTitle": "8 months in role                     8 months in company",
    "leadPanel": "/sales/lead/ACwAAAaaOrgB94tkG9AoTq2AK3GlTAMBYxF_9Jo,NAME_SEARCH,rOFE?_ntb=%2Fb3tu0iwTKeaQVASZGH%2F8w%3D%3D",
    "location": "Hampton Roads, Virginia Metropolitan Area",
    "name": "Laurie Bossard",
    "photo": null,
    "title": "Senior Buyer of Mens, Ladies and Kids Footwear and Socks & Hosiery"
  },
  {
    "about": "About:        see more",
    "company": "Lids",
    "jobTitle": "8 months in role                    2 years  in company",
    "leadPanel": "/sales/lead/ACwAAC0TLRUBwMITmZd7XDAeTc6YNU9eQRk5VOw,NAME_SEARCH,DqjS?_ntb=%2Fb3tu0iwTKeaQVASZGH%2F8w%3D%3D",
    "location": "Indianapolis, Indiana, United States",
    "name": "Mark Desmond Thompson",
    "photo": "https://media.licdn.com/dms/image/C5603AQFSzbsOSo20fg/profile-displayphoto-shrink_100_100/0/1516787535350?e=1714608000&v=beta&t=Fs-pt_-aktUH38Kjcs-9a3EBgJJLYLQH4bJJY_mizOQ",
    "title": "Buyer"
  },
  {
    "about": "",
    "company": "CarMax",
    "jobTitle": "11 years 6 months in role                    16 years 3 months in company",
    "leadPanel": "/sales/lead/ACwAADGN4bcB7pMxsiDnWQ_DzX8lWyrB5-xr8vE,NAME_SEARCH,3p89?_ntb=%2Fb3tu0iwTKeaQVASZGH%2F8w%3D%3D",
    "location": "United States",
    "name": "Ariel Musa",
    "photo": null,
    "title": "Buyer"
  },
  {
    "about": "",
    "company": "Ross Stores, Inc.",
    "jobTitle": "3 years 1 month in role                    7 years 5 months in company",
    "leadPanel": "/sales/lead/ACwAAB3T7kgB81tZNnByEMiW_m-n5EiT9pBfxs0,NAME_SEARCH,J1EW?_ntb=%2Fb3tu0iwTKeaQVASZGH%2F8w%3D%3D",
    "location": "Los Angeles, California, United States",
    "name": "Justine Estrada",
    "photo": "https://media.licdn.com/dms/image/D4E03AQHU4FBqf2LMWw/profile-displayphoto-shrink_100_100/0/1682098452956?e=1714608000&v=beta&t=KFDwpxEsZxnnPaAIpb2UaVNHtWTDaaXazz5RMjsPmLM",
    "title": "Buyer"
  },
  {
    "about": "About:        see more",
    "company": "Jetro Restaurant Depot",
    "jobTitle": "3 years 2 months in role                    3 years 2 months in company",
    "leadPanel": "/sales/lead/ACwAABAk-H4BmV1mYuKH7_-50tyZ6KLmt0gZU3s,NAME_SEARCH,sGb9?_ntb=%2Fb3tu0iwTKeaQVASZGH%2F8w%3D%3D",
    "location": "Los Angeles Metropolitan Area",
    "name": "Chris Vasquez",
    "photo": null,
    "title": "Buyer"
  },
  {
    "about": "",
    "company": "Ferrero",
    "jobTitle": "2 years 8 months in role                    2 years 8 months in company",
    "leadPanel": "/sales/lead/ACwAAAHIC_wBZau4qa47AN9KaUXplWDXumnZwHI,NAME_SEARCH,SVkD?_ntb=%2Fb3tu0iwTKeaQVASZGH%2F8w%3D%3D",
    "location": "Palm Beach, Florida, United States",
    "name": "Michelle Kielb",
    "photo": "https://media.licdn.com/dms/image/C5103AQF-Sb5vdxVAsg/profile-displayphoto-shrink_100_100/0/1516875985299?e=1714608000&v=beta&t=AVZNcfTs_WfEcZ7Dq3de_XE0TXs6OR42NVU20wbD6lQ",
    "title": "Buyer, Sales Lead"
  },
  {
    "about": "About:        see more",
    "company": "Ross Stores, Inc.",
    "jobTitle": "1 year 5 months in role                    1 year 5 months in company",
    "leadPanel": "/sales/lead/ACwAAAIFxdoB3niPQPUh8AxFHDOnEnUv4Zjy75U,NAME_SEARCH,LEeU?_ntb=%2Fb3tu0iwTKeaQVASZGH%2F8w%3D%3D",
    "location": "South Amboy, New Jersey, United States",
    "name": "Melissa Sanders",
    "photo": null,
    "title": "Buyer"
  },
  {
    "about": "About:        see more",
    "company": "Meijer",
    "jobTitle": "1 year 9 months in role                    1 year 9 months in company",
    "leadPanel": "/sales/lead/ACwAAAkSWwgBAJGiznMjnTOs2ukoZsjsjY4uUFc,NAME_SEARCH,LwFK?_ntb=%2Fb3tu0iwTKeaQVASZGH%2F8w%3D%3D",
    "location": "New York City Metropolitan Area",
    "name": "Amanda Prince",
    "photo": "https://media.licdn.com/dms/image/C5603AQGieUgks2qgnA/profile-displayphoto-shrink_100_100/0/1559420651791?e=1714608000&v=beta&t=nD9LeXX24kBqa6hrc53XUhrxQfT1eIGbJiZ-S5w4PwM",
    "title": "Buyer"
  },
  {
    "about": "",
    "company": "Famous Footwear",
    "jobTitle": "12 years 9 months in role                    21 years 1 month in company",
    "leadPanel": "/sales/lead/ACwAAAUGMxMBS8aWgvg7VivF3UG70XOnOgV_BLY,NAME_SEARCH,0gEM?_ntb=%2Fb3tu0iwTKeaQVASZGH%2F8w%3D%3D",
    "location": "Ada, Michigan, United States",
    "name": "Jeff Lynch",
    "photo": null,
    "title": "Buyer/Merchandiser Garden Center-Outdoor Live Plants, Bagged Mulches, Soil, Charcoal and Fire Logs"
  },
  {
    "about": "",
    "company": "CarMax",
    "jobTitle": "1 year 8 months in role                    1 year 8 months in company",
    "leadPanel": "/sales/lead/ACwAAApCnncBJKYKvPL6Mpa4N3k7XMR-X6w8uWs,NAME_SEARCH,O7pK?_ntb=%2Fb3tu0iwTKeaQVASZGH%2F8w%3D%3D",
    "location": "Bellflower, California, United States",
    "name": "Phillip DeOchoa",
    "photo": "https://media.licdn.com/dms/image/C5603AQHU4oNLyzb3AQ/profile-displayphoto-shrink_200_200/0/1517678482408?e=1714608000&v=beta&t=L2LJlCaQl_0Dmk9TBABDqOFim07cjHHPIgTNVss1H-8",
    "title": "Produce Buyer"
  },
  {
    "about": "",
    "company": "United Stores Inc.",
    "jobTitle": "4 years 10 months in role                    15 years 10 months in company",
    "leadPanel": "/sales/lead/ACwAAAHJObgBc-BvixiPv7JFZukVniU_Tn5yfvo,NAME_SEARCH,33tY?_ntb=%2Fb3tu0iwTKeaQVASZGH%2F8w%3D%3D",
    "location": "St Louis, Missouri, United States",
    "name": "Tim Paunovich",
    "photo": null,
    "title": "Buyer, Mens Non-Athletic"
  },
  {
    "about": "",
    "company": "",
    "jobTitle": "3 years 6 months in role                    3 years 6 months in company",
    "leadPanel": "/sales/lead/ACwAAC98poEBIxNLTxnbLr_6oiwcdTdmP_FSTgg,OUT_OF_NETWORK,V9I_?_ntb=%2Fb3tu0iwTKeaQVASZGH%2F8w%3D%3D",
    "location": "Roanoke, Virginia, United States",
    "name": "Sean Finnegan",
    "photo": "https://media.licdn.com/dms/image/C4D03AQEQ8EQG8o8-DA/profile-displayphoto-shrink_100_100/0/1603367901295?e=1714608000&v=beta&t=r-4C6wZUTwbtcUqhnuQ0bZLUh1aXqQJgdhliFJtpyUQ",
    "title": "Buyer"
  },
  {
    "about": "About:        see more",
    "company": "",
    "jobTitle": "3 months in role                     3 months in company",
    "leadPanel": "/sales/lead/ACwAACGBY8EBULncE9Cci3JHS85ryA15hmWng1s,NAME_SEARCH,SP5d?_ntb=%2Fb3tu0iwTKeaQVASZGH%2F8w%3D%3D",
    "location": "Los Angeles Metropolitan Area",
    "name": "Gabriel Sandoval",
    "photo": null,
    "title": "Buyer"
  },
  {
    "about": "",
    "company": "CarMax",
    "jobTitle": "in role                      in company",
    "leadPanel": "/sales/lead/ACwAAAIMUNMBS9ueAmwZTuW68hvwcPflv66HK94,OUT_OF_NETWORK,2wpl?_ntb=%2Fb3tu0iwTKeaQVASZGH%2F8w%3D%3D",
    "location": "New York, New York, United States",
    "name": "Sylvia Ferrari",
    "photo": "https://media.licdn.com/dms/image/D4E03AQHU4FBqf2LMWw/profile-displayphoto-shrink_100_100/0/1682098452956?e=1714608000&v=beta&t=KFDwpxEsZxnnPaAIpb2UaVNHtWTDaaXazz5RMjsPmLM",
    "title": "Buyer"
  },
  {
    "about": "",
    "company": "Replacements, Ltd.",
    "jobTitle": "5 years 1 month in role                    5 years 1 month in company",
    "leadPanel": "/sales/lead/ACwAAAWewJcBT-XXtZ5XBAnBlRn8ER5XrbL9Z88,NAME_SEARCH,Wmk0?_ntb=%2Fb3tu0iwTKeaQVASZGH%2F8w%3D%3D",
    "location": "United States",
    "name": "Jeanna Palumbo",
    "photo": null,
    "title": "Founder | Buyer"
  },
  {
    "about": "About:        see more",
    "company": "Texas Biomedical Research Institute",
    "jobTitle": "11 years 7 months in role                    11 years 7 months in company",
    "leadPanel": "/sales/lead/ACwAAAWtz-UBcifHOK4vxHSnYUKrK1H5Ewk1jOE,OUT_OF_NETWORK,aE6T?_ntb=%2Fb3tu0iwTKeaQVASZGH%2F8w%3D%3D",
    "location": "Carrollton, Texas, United States",
    "name": "Keith Jones",
    "photo": "data:image/gif;base64,R0lGODlhAQABAIAAAAAAAP///yH5BAEAAAAALAAAAAABAAEAAAIBRAA7",
    "title": "Buyer"
  },
  {
    "about": "About:        see more",
    "company": "Legends",
    "jobTitle": "2 years 2 months in role                    2 years 2 months in company",
    "leadPanel": "/sales/lead/ACwAAB5-p3UBGmIUhSdY9BzNsjvnJwNma4zmhMA,NAME_SEARCH,_s5e?_ntb=%2Fb3tu0iwTKeaQVASZGH%2F8w%3D%3D",
    "location": "Asheboro, North Carolina, United States",
    "name": "Christopher Toro",
    "photo": null,
    "title": "Watch Buyer/ Watchmaker"
  },
  {
    "about": "",
    "company": "NAVY EXCHANGE SERVICE COMMAND (NEXCOM)",
    "jobTitle": "25 years 1 month in role                    25 years 1 month in company",
    "leadPanel": "/sales/lead/ACwAAAK7CKgB2iUtMos2Lnr9F7liL23GtJyXSms,NAME_SEARCH,V99x?_ntb=%2Fb3tu0iwTKeaQVASZGH%2F8w%3D%3D",
    "location": "Memphis, Tennessee, United States",
    "name": "Jim Carnes",
    "photo": "https://media.licdn.com/dms/image/C4D03AQEVagDrRkfl3w/profile-displayphoto-shrink_100_100/0/1642174762226?e=1714608000&v=beta&t=ghgKKwveSHKrhkKFJN1CELJrMwXeH6_K2EkZIBOrbPA",
    "title": "Buyer"
  },
  {
    "about": "About:        see more",
    "company": "RCD RV Supercenter",
    "jobTitle": "1 year 2 months in role                    1 year 2 months in company",
    "leadPanel": "/sales/lead/ACwAAAXztBsBOcBcxM3TAo8GnV_gYK5e9GiJQ0c,NAME_SEARCH,H43v?_ntb=%2Fb3tu0iwTKeaQVASZGH%2F8w%3D%3D",
    "location": "San Antonio, Texas, United States",
    "name": "Claudia Beltran",
    "photo": null,
    "title": "Buyer"
  },
  {
    "about": "",
    "company": "DICK'S Sporting Goods",
    "jobTitle": "6 months in role                    2 years 3 months in company",
    "leadPanel": "/sales/lead/ACwAAC3N-OABDJoo7ZvJtZCOhorz_B32xEjOEu8,NAME_SEARCH,EF4W?_ntb=%2Fb3tu0iwTKeaQVASZGH%2F8w%3D%3D",
    "location": "Indianapolis, Indiana, United States",
    "name": "Abby Lambright",
    "photo": "https://media.licdn.com/dms/image/C4D03AQHxP-FN7q7BDQ/profile-displayphoto-shrink_100_100/0/1517475932205?e=1714608000&v=beta&t=j0zjpaNcrvE0rIcj6pYIlX6eeagfyGxSeHwL2MELTPg",
    "title": "Buyer"
  },
  {
    "about": "About:        see more",
    "company": "",
    "jobTitle": "1 year 6 months in role                    1 year 6 months in company",
    "leadPanel": "/sales/lead/ACwAAApgIa8BztOP1LcjTxaUfnKkz_4OkwiYNbM,NAME_SEARCH,RsqM?_ntb=%2Fb3tu0iwTKeaQVASZGH%2F8w%3D%3D",
    "location": "Raleigh-Durham-Chapel Hill Area",
    "name": "Thomas Dunbar",
    "photo": null,
    "title": "Buyer Audio & Smart Home"
  },
  {
    "about": "About:        see more",
    "company": "",
    "jobTitle": "1 year 11 months in role                    1 year 11 months in company",
    "leadPanel": "/sales/lead/ACwAAA2wCyABgnDltpN4FkOQtBkpUKbikq6_HjU,NAME_SEARCH,95p9?_ntb=%2Fb3tu0iwTKeaQVASZGH%2F8w%3D%3D",
    "location": "Columbus, Ohio, United States",
    "name": "Brad Moorehead",
    "photo": "https://media.licdn.com/dms/image/C5103AQGBzawvAsU-Lg/profile-displayphoto-shrink_100_100/0/1517229763596?e=1714608000&v=beta&t=D0xmFfN1HEjXpGA0dDXeEEBE7iZ30j_bWAYWFrAjyv0",
    "title": "Buyer"
  },
  {
    "about": "",
    "company": "",
    "jobTitle": "1 year 7 months in role                    5 years 2 months in company",
    "leadPanel": "/sales/lead/ACwAACN1QE8Bm1eiKo7087sOiYy6YuKAs5Agr8Y,NAME_SEARCH,ljsd?_ntb=%2Fb3tu0iwTKeaQVASZGH%2F8w%3D%3D",
    "location": "Fort Lauderdale, Florida, United States",
    "name": "Honey Smith",
    "photo": null,
    "title": "Ast. Buyer"
  },
  {
    "about": "About:        see more",
    "company": "The Edit Shops",
    "jobTitle": "2 years 5 months in role                    2 years 5 months in company",
    "leadPanel": "/sales/lead/ACwAACwJGqwBTxH93UswOJQDouNb0DL7MJA8Hvw,NAME_SEARCH,xSml?_ntb=%2Fb3tu0iwTKeaQVASZGH%2F8w%3D%3D",
    "location": "Dallas-Fort Worth Metroplex",
    "name": "Tifany R.",
    "photo": "https://media.licdn.com/dms/image/D4E03AQHU4FBqf2LMWw/profile-displayphoto-shrink_100_100/0/1682098452956?e=1714608000&v=beta&t=KFDwpxEsZxnnPaAIpb2UaVNHtWTDaaXazz5RMjsPmLM",
    "title": "Buyer"
  },
  {
    "about": "About:        see more",
    "company": "Stitch Fix",
    "jobTitle": "5 months in role                    2 years 5 months in company",
    "leadPanel": "/sales/lead/ACwAABesibsBtxzsoSYIaS42WPax3mhRJwre1CA,NAME_SEARCH,R_PD?_ntb=%2Fb3tu0iwTKeaQVASZGH%2F8w%3D%3D",
    "location": "San Francisco, California, United States",
    "name": "Trent Carlson",
    "photo": null,
    "title": "Buyer - Women's Handbags, Jewelry & Accessories"
  },
  {
    "about": "",
    "company": "Wheels, Inc.",
    "jobTitle": "5 years 1 month in role                    5 years 1 month in company",
    "leadPanel": "/sales/lead/ACwAAAouq8cBxC6_cSEpaemjObx-kbAHxXFP2CU,NAME_SEARCH,TdfV?_ntb=%2Fb3tu0iwTKeaQVASZGH%2F8w%3D%3D",
    "location": "West Dundee, Illinois, United States",
    "name": "Alyssa Pociask",
    "photo": "https://media.licdn.com/dms/image/C5603AQEIJ1tyEEJ9QQ/profile-displayphoto-shrink_100_100/0/1559002320732?e=1714608000&v=beta&t=8CQ0cO6Su58pOA2O5Xq9OgSm-Dum4Ji9KQR9rUc-JAc",
    "title": "OOS Buyer"
  },
  {
    "about": "",
    "company": "EVEREVE",
    "jobTitle": "3 months in role                     3 months in company",
    "leadPanel": "/sales/lead/ACwAABlTGv8B4WSpx71wl6wgpcAiCY5-ZpPIF5k,NAME_SEARCH,DU0Q?_ntb=%2Fb3tu0iwTKeaQVASZGH%2F8w%3D%3D",
    "location": "Minneapolis, Minnesota, United States",
    "name": "Taylor Robarge",
    "photo": null,
    "title": "Stylist"
  },
  {
    "about": "About:        see more",
    "company": "Byrider",
    "jobTitle": "2 years 6 months in role                    2 years 6 months in company",
    "leadPanel": "/sales/lead/ACwAAB8f2MkBpdw9wo97-7mBX_V_QmKdSWDPX8Y,NAME_SEARCH,Ohjj?_ntb=%2Fb3tu0iwTKeaQVASZGH%2F8w%3D%3D",
    "location": "Greater Palm Bay-Melbourne-Titusville Area",
    "name": "Avery Dirr",
    "photo": "https://media.licdn.com/dms/image/D5603AQGmuguCC9VUrw/profile-displayphoto-shrink_100_100/0/1687382729457?e=1714608000&v=beta&t=UljvVdgwYAAL3ZiWG5AKPbIIG6zGoHTWh6_BofioSC8",
    "title": "Field Buyer"
  },
  {
    "about": "",
    "company": "Etro",
    "jobTitle": "1 year 11 months in role                    1 year 11 months in company",
    "leadPanel": "/sales/lead/ACwAABVW5lgBlCbay3KqgDAGaEN4wk8aJLu2Y9Y,NAME_SEARCH,rQ6w?_ntb=%2Fb3tu0iwTKeaQVASZGH%2F8w%3D%3D",
    "location": "New York City Metropolitan Area",
    "name": "Jillian Pascual",
    "photo": null,
    "title": "Buyer"
  },
  {
    "about": "",
    "company": "The TJX Companies, Inc.",
    "jobTitle": "5 months in role                    6 years 9 months in company",
    "leadPanel": "/sales/lead/ACwAABGut0MB6arjFARqg9SKUiS8dA8of5jzuiw,NAME_SEARCH,vXNw?_ntb=%2Fb3tu0iwTKeaQVASZGH%2F8w%3D%3D",
    "location": "New York City Metropolitan Area",
    "name": "Michael Gasiewski",
    "photo": "https://media.licdn.com/dms/image/C4E03AQG9zSABbAmSFw/profile-displayphoto-shrink_200_200/0/1534209197740?e=1714608000&v=beta&t=RPaXNOkXotAUjcHwkygDa35wK7e_fSK1VLfaklH7rBg",
    "title": "Buyer"
  },
  {
    "about": "",
    "company": "REI",
    "jobTitle": "2 months in role                    6 years 10 months in company",
    "leadPanel": "/sales/lead/ACwAAAaPV5oBb2hxygSKE2pC_hM8WAHLIxcXQ44,NAME_SEARCH,UKws?_ntb=%2Fb3tu0iwTKeaQVASZGH%2F8w%3D%3D",
    "location": "Seattle, Washington, United States",
    "name": "Jen Gousman",
    "photo": null,
    "title": "Buyer - Womens Lifestyle & Hike Footwear"
  },
  {
    "about": "",
    "company": "Novelty Express",
    "jobTitle": "2 years 10 months in role                    5 years 6 months in company",
    "leadPanel": "/sales/lead/ACwAACGkhkcBeFCvdRBSLJmEf-DyldYwM5WB-wU,NAME_SEARCH,j7lW?_ntb=%2Fb3tu0iwTKeaQVASZGH%2F8w%3D%3D",
    "location": "Henderson, North Carolina, United States",
    "name": "Whitney Reed",
    "photo": "https://media.licdn.com/dms/image/D5603AQG0ShHU44u1JA/profile-displayphoto-shrink_100_100/0/1701275543985?e=1714608000&v=beta&t=CqAuqdbPpiLDZbvoLGmN-PYglECDV2_QmphSd9IJic4",
    "title": "Buyer"
  },
  {
    "about": "About:        see more",
    "company": "CarMax",
    "jobTitle": "9 months in role                    10 years 11 months in company",
    "leadPanel": "/sales/lead/ACwAAAlNq08B38qrSVNUOWzuVBP2u45r0YrfwPY,NAME_SEARCH,wRlM?_ntb=%2Fb3tu0iwTKeaQVASZGH%2F8w%3D%3D",
    "location": "Atlanta, Georgia, United States",
    "name": "Andrew Wagner",
    "photo": null,
    "title": "Buyer"
  },
  {
    "about": "",
    "company": "CarMax",
    "jobTitle": "3 years 5 months in role                    4 years 1 month in company",
    "leadPanel": "/sales/lead/ACwAAC0TcEoB2gVUQb0RGvb7fcLzSbb9wjAdGIE,NAME_SEARCH,uWbm?_ntb=%2Fb3tu0iwTKeaQVASZGH%2F8w%3D%3D",
    "location": "Dallas-Fort Worth Metroplex",
    "name": "Frederick Burns II",
    "photo": "https://media.licdn.com/dms/image/D4E03AQHU4FBqf2LMWw/profile-displayphoto-shrink_100_100/0/1682098452956?e=1714608000&v=beta&t=KFDwpxEsZxnnPaAIpb2UaVNHtWTDaaXazz5RMjsPmLM",
    "title": "Buyer"
  },
  {
    "about": "",
    "company": "Steve Madden",
    "jobTitle": "1 year 5 months in role                    4 years 9 months in company",
    "leadPanel": "/sales/lead/ACwAAB8WqywBkPGHFliXiBpnM19vOntUSNhkjtg,NAME_SEARCH,0mQ0?_ntb=%2Fb3tu0iwTKeaQVASZGH%2F8w%3D%3D",
    "location": "Woodbury, New York, United States",
    "name": "Katie Cirella",
    "photo": null,
    "title": "Buyer"
  },
  {
    "about": "About:        see more",
    "company": "Hillphoenix",
    "jobTitle": "9 months in role                    3 years 4 months in company",
    "leadPanel": "/sales/lead/ACwAACCyqZwBBjE67ssylfiQNvbZTh62kenCDg0,NAME_SEARCH,1BFv?_ntb=%2Fb3tu0iwTKeaQVASZGH%2F8w%3D%3D",
    "location": "Centerville, Iowa, United States",
    "name": "Stacy Leffler",
    "photo": "https://media.licdn.com/dms/image/D5603AQHOJEKhnrMzxw/profile-displayphoto-shrink_100_100/0/1686158433515?e=1714608000&v=beta&t=Vdu1r6ZLjkMUSybyN7JewkJOMA-xFNOna34gCXrLcck",
    "title": "Purchaser"
  },
  {
    "about": "",
    "company": "Zulily",
    "jobTitle": "1 year 8 months in role                    3 years 3 months in company",
    "leadPanel": "/sales/lead/ACwAACpxnpwBKgNiXxWi-eSkxuzpW6O6Glp-p4o,NAME_SEARCH,tB_J?_ntb=%2Fb3tu0iwTKeaQVASZGH%2F8w%3D%3D",
    "location": "Greater Seattle Area",
    "name": "Robin Young",
    "photo": null,
    "title": "Buyer"
  },
  {
    "about": "",
    "company": "Kinter",
    "jobTitle": "2 years 11 months in role                    2 years 11 months in company",
    "leadPanel": "/sales/lead/ACwAACvXJX0BVjYSHtX6Dg9sbSQwFFkOPsK4KWM,NAME_SEARCH,4jax?_ntb=%2Fb3tu0iwTKeaQVASZGH%2F8w%3D%3D",
    "location": "Greater Chicago Area",
    "name": "Jeffrey Forgue",
    "photo": "https://media.licdn.com/dms/image/C4D03AQGbSBRg4UuhNA/profile-displayphoto-shrink_100_100/0/1614800200460?e=1714608000&v=beta&t=NNwNayPinjbkXCYH1lLyPDrtdAgZoIiWXZqczJDYyoA",
    "title": "Buyer"
  },
  {
    "about": "",
    "company": "Burlington Stores, Inc.",
    "jobTitle": "4 years 8 months in role                    11 years 10 months in company",
    "leadPanel": "/sales/lead/ACwAAAPhBAQBJuctEXr80hg1fO45em6ArvJAYxE,NAME_SEARCH,gZqp?_ntb=%2Fb3tu0iwTKeaQVASZGH%2F8w%3D%3D",
    "location": "Philadelphia, Pennsylvania, United States",
    "name": "Bonnie Catts",
    "photo": null,
    "title": "Buyer"
  },
  {
    "about": "",
    "company": "CarMax",
    "jobTitle": "3 years 1 month in role                    3 years 9 months in company",
    "leadPanel": "/sales/lead/ACwAAALvNgkBQzpILWrZ3S4Gy1q4Pi5uDZfuB3k,NAME_SEARCH,7EyJ?_ntb=%2Fb3tu0iwTKeaQVASZGH%2F8w%3D%3D",
    "location": "Indianapolis, Indiana, United States",
    "name": "Thad Ryan",
    "photo": "https://media.licdn.com/dms/image/C5603AQHsYJgN8TdJAQ/profile-displayphoto-shrink_100_100/0/1618335056898?e=1714608000&v=beta&t=ohi6qzseO0LMDC-mBEm65kDjOydneS-l-cAhH4WigP8",
    "title": "Buyer"
  },
  {
    "about": "",
    "company": "Main Street Fibers",
    "jobTitle": "1 year 10 months in role                    1 year 10 months in company",
    "leadPanel": "/sales/lead/ACwAAAPc5XcBiAuUSd4GS_U7jMAXqaDRaoIz5Gg,NAME_SEARCH,l5Ke?_ntb=%2Fb3tu0iwTKeaQVASZGH%2F8w%3D%3D",
    "location": "Los Angeles Metropolitan Area",
    "name": "Anna R.",
    "photo": null,
    "title": "Buyer/Sales"
  },
  {
    "about": "About:        see more",
    "company": "Inverness Club",
    "jobTitle": "2 years 1 month in role                    4 years 2 months in company",
    "leadPanel": "/sales/lead/ACwAAA-aZJEBEs8OP1X4LalifJd6Bt6ygyWHa9w,NAME_SEARCH,YxE2?_ntb=%2Fb3tu0iwTKeaQVASZGH%2F8w%3D%3D",
    "location": "Toledo, Ohio, United States",
    "name": "Brooke Oakley, AGM",
    "photo": "data:image/gif;base64,R0lGODlhAQABAIAAAAAAAP///yH5BAEAAAAALAAAAAABAAEAAAIBRAA7",
    "title": "Buyer / Merchandiser"
  },
  {
    "about": "",
    "company": "",
    "jobTitle": "3 years 6 months in role                    3 years 6 months in company",
    "leadPanel": "/sales/lead/ACwAAAXTtzcBJQ9HYdto3X5PE8NSx58fkEu_Fig,NAME_SEARCH,aZlN?_ntb=%2Fb3tu0iwTKeaQVASZGH%2F8w%3D%3D",
    "location": "Florence, New Jersey, United States",
    "name": "Randy Wooden",
    "photo": null,
    "title": "GMM  Buyer"
  },
  {
    "about": "About:        see more",
    "company": "Ross Stores, Inc.",
    "jobTitle": "5 years 2 months in role                    10 years 7 months in company",
    "leadPanel": "/sales/lead/ACwAAAwwUFQBNH1wZGgYa1Oe2pYT1Jr3VAb3h5A,NAME_SEARCH,8ICf?_ntb=%2Fb3tu0iwTKeaQVASZGH%2F8w%3D%3D",
    "location": "New York City Metropolitan Area",
    "name": "Alexander Bey",
    "photo": "https://media.licdn.com/dms/image/D4E03AQHU4FBqf2LMWw/profile-displayphoto-shrink_100_100/0/1682098452956?e=1714608000&v=beta&t=KFDwpxEsZxnnPaAIpb2UaVNHtWTDaaXazz5RMjsPmLM",
    "title": "Buyer, Mens Contemporary Private Label Collections"
  },
  {
    "about": "",
    "company": "Saks OFF 5TH",
    "jobTitle": "9 months in role                    3 years 5 months in company",
    "leadPanel": "/sales/lead/ACwAAA1ZiegBo-TWFxjx-mBTpo9PaNZXc8BkDQk,NAME_SEARCH,D6_U?_ntb=%2Fb3tu0iwTKeaQVASZGH%2F8w%3D%3D",
    "location": "New York City Metropolitan Area",
    "name": "Kelsey Nieves",
    "photo": null,
    "title": "Buyer- Womens Active & Trend"
  },
  {
    "about": "",
    "company": "Prevea Health",
    "jobTitle": "3 years 6 months in role                    3 years 6 months in company",
    "leadPanel": "/sales/lead/ACwAACHhFz8BfYhUnIoOtHlnk46KQwvoFboXxfY,OUT_OF_NETWORK,52_Q?_ntb=%2Fb3tu0iwTKeaQVASZGH%2F8w%3D%3D",
    "location": "Green Bay, Wisconsin, United States",
    "name": "Kelly Flynn",
    "photo": "https://media.licdn.com/dms/image/D4E03AQEPdbm18fHnAw/profile-displayphoto-shrink_100_100/0/1696524031836?e=1714608000&v=beta&t=Imdw6iVahW5rjBE0yRJds1fYDxx9lZO80EFQRMZPt0E",
    "title": "Buyer"
  },
  {
    "about": "About:        see more",
    "company": "Sally Beauty",
    "jobTitle": "10 months in role                     10 months in company",
    "leadPanel": "/sales/lead/ACwAAAbZ7aQB0qMPGvOoVGDUleCyW6DG1jXMGOU,NAME_SEARCH,IrmG?_ntb=%2Fb3tu0iwTKeaQVASZGH%2F8w%3D%3D",
    "location": "Roanoke, Texas, United States",
    "name": "Emma Griffin",
    "photo": null,
    "title": "Buyer"
  },
  {
    "about": "",
    "company": "Conte's Bike Shop",
    "jobTitle": "3 months in role                    3 years 8 months in company",
    "leadPanel": "/sales/lead/ACwAABqkSI0Bfg4ORj6InimgqCgUOBV2a8eJlqk,NAME_SEARCH,hu9u?_ntb=%2Fb3tu0iwTKeaQVASZGH%2F8w%3D%3D",
    "location": "Tucson, Arizona, United States",
    "name": "Cole Ebenkamp",
    "photo": "https://media.licdn.com/dms/image/D4E03AQEJtfi9QefnLQ/profile-displayphoto-shrink_100_100/0/1699840639283?e=1714608000&v=beta&t=-VVwwcdkPE6DZuOfDiUzlPAgg8uhuPF955bamxHSmCo",
    "title": "Buyer"
  },
  {
    "about": "About:        see more",
    "company": "Northeast Numismatics",
    "jobTitle": "5 years  in role                    5 years  in company",
    "leadPanel": "/sales/lead/ACwAAC4qj1kBI_HRCffqvoM-MabwcZHtUk7mw74,NAME_SEARCH,JfYt?_ntb=%2Fb3tu0iwTKeaQVASZGH%2F8w%3D%3D",
    "location": "Greater Boston",
    "name": "Frank Sawin",
    "photo": null,
    "title": "Buyer and Numismatic Researcher"
  },
  {
    "about": "About:        see more",
    "company": "Whole Foods Market",
    "jobTitle": "11 years 2 months in role                    14 years 4 months in company",
    "leadPanel": "/sales/lead/ACwAABIbqHgB6gsEeV3_TJrGAXHgOAv_nm868N8,NAME_SEARCH,cHFn?_ntb=%2Fb3tu0iwTKeaQVASZGH%2F8w%3D%3D",
    "location": "Portland, Oregon, United States",
    "name": "Matt B.",
    "photo": "data:image/gif;base64,R0lGODlhAQABAIAAAAAAAP///yH5BAEAAAAALAAAAAABAAEAAAIBRAA7",
    "title": "Buyer"
  },
  {
    "about": "About:        see more",
    "company": "SNIPES",
    "jobTitle": "2 years 3 months in role                    2 years 3 months in company",
    "leadPanel": "/sales/lead/ACwAABUYx0oB5AVBuW-6CHeuqv0V4kzsulxZrxs,NAME_SEARCH,fHMZ?_ntb=%2Fb3tu0iwTKeaQVASZGH%2F8w%3D%3D",
    "location": "New York, New York, United States",
    "name": "Stefanie Rabiner",
    "photo": null,
    "title": "Buyer"
  },
  {
    "about": "",
    "company": "Ross Stores, Inc.",
    "jobTitle": "4 years 1 month in role                    8 years 1 month in company",
    "leadPanel": "/sales/lead/ACwAAASWtN0BY5uyrwIv38hKsxfCu68nyy5HPCM,NAME_SEARCH,h26-?_ntb=%2Fb3tu0iwTKeaQVASZGH%2F8w%3D%3D",
    "location": "Greater Boston",
    "name": "Jennifer Cerra",
    "photo": "https://media.licdn.com/dms/image/D5603AQGMwcNWP6oMgA/profile-displayphoto-shrink_100_100/0/1675273552213?e=1714608000&v=beta&t=LnZq8AjuC3JmLvPTXB1vN_XDDppwxG9KIvrqvLFBOXc",
    "title": "Buyer"
  },
  {
    "about": "About:        see more",
    "company": "",
    "jobTitle": "1 year 6 months in role                    1 year 6 months in company",
    "leadPanel": "/sales/lead/ACwAAAEShZMB5mtF1y9FAiVy5G71yzAFP5j3fp0,NAME_SEARCH,-Nmt?_ntb=%2Fb3tu0iwTKeaQVASZGH%2F8w%3D%3D",
    "location": "Floral Park, New York, United States",
    "name": "Nancy Granatoor",
    "photo": null,
    "title": "Director of Product Development and Production"
  },
  {
    "about": "About:        see more",
    "company": "Dillard's Inc.",
    "jobTitle": "2 years 5 months in role                    2 years 5 months in company",
    "leadPanel": "/sales/lead/ACwAAAvY9IsBF_oFeGDi617gO5KSCdkyiXUmdbc,NAME_SEARCH,8lBb?_ntb=%2Fb3tu0iwTKeaQVASZGH%2F8w%3D%3D",
    "location": "Clearwater, Florida, United States",
    "name": "Robin Brown",
    "photo": "https://media.licdn.com/dms/image/D4E03AQHU4FBqf2LMWw/profile-displayphoto-shrink_100_100/0/1682098452956?e=1714608000&v=beta&t=KFDwpxEsZxnnPaAIpb2UaVNHtWTDaaXazz5RMjsPmLM",
    "title": "Buyer"
  },
  {
    "about": "",
    "company": "Bruckner Supply",
    "jobTitle": "in role                      in company",
    "leadPanel": "/sales/lead/ACwAABEyTz8B_u3QNg_jelRZ1ajKJ1o15Orx4AU,OUT_OF_NETWORK,mW9V?_ntb=%2Fb3tu0iwTKeaQVASZGH%2F8w%3D%3D",
    "location": "Manhasset, New York, United States",
    "name": "Pat Brauer",
    "photo": null,
    "title": "Buyer"
  },
  {
    "about": "",
    "company": "Schnuck Markets, Inc.",
    "jobTitle": "6 years 6 months in role                    26 years 2 months in company",
    "leadPanel": "/sales/lead/ACwAAB4iURAB4DHK6S6MaWxWN22BU3Qo3z7bC4M,NAME_SEARCH,Zlci?_ntb=%2Fb3tu0iwTKeaQVASZGH%2F8w%3D%3D",
    "location": "Troy, Illinois, United States",
    "name": "Brian Quinn",
    "photo": "https://media.licdn.com/dms/image/C5103AQG7rIjmdkM1BQ/profile-displayphoto-shrink_100_100/0/1516931480096?e=1714608000&v=beta&t=hgri3vChGGT0dI2dDZKBvV4NXqkpK_Y8XUSUESpa_P0",
    "title": "Buyer analyst"
  },
  {
    "about": "About:        see more",
    "company": "Chef Mart",
    "jobTitle": "3 years  in role                    3 years  in company",
    "leadPanel": "/sales/lead/ACwAACryKc0BGja5UB4KfWr227b265Q_BBKXrBA,OUT_OF_NETWORK,1pZs?_ntb=%2Fb3tu0iwTKeaQVASZGH%2F8w%3D%3D",
    "location": "Houston, Texas, United States",
    "name": "Jancarlos M.",
    "photo": null,
    "title": "Buyer"
  },
  {
    "about": "",
    "company": "Giant Food",
    "jobTitle": "2 years 1 month in role                    2 years 1 month in company",
    "leadPanel": "/sales/lead/ACwAABDmRMMBgcB8INO1EFJ4iDOYpRiD6UxqReI,OUT_OF_NETWORK,FIbm?_ntb=%2Fb3tu0iwTKeaQVASZGH%2F8w%3D%3D",
    "location": "Washington DC-Baltimore Area",
    "name": "madison calebaugh",
    "photo": "https://media.licdn.com/dms/image/C4E03AQFLFGIVFRz0qw/profile-displayphoto-shrink_100_100/0/1525373832267?e=1714608000&v=beta&t=JhYubVip9cTv8NkyHjcbSVr-o1GNNsB5BACMpIxOLX0",
    "title": "Meat Buyer"
  },
  {
    "about": "",
    "company": "U.S. Coast Guard Community Services Command (CGCSC)",
    "jobTitle": "12 years 2 months in role                    17 years  in company",
    "leadPanel": "/sales/lead/ACwAACuumzwBd89FZ0t8YU5q5iDH5cWbtQESmgw,OUT_OF_NETWORK,4nt1?_ntb=%2Fb3tu0iwTKeaQVASZGH%2F8w%3D%3D",
    "location": "Hampton Roads, Virginia Metropolitan Area",
    "name": "Dawn Stith",
    "photo": null,
    "title": "Buyer"
  },
  {
    "about": "",
    "company": "CarMax",
    "jobTitle": "3 years 5 months in role                    3 years 5 months in company",
    "leadPanel": "/sales/lead/ACwAACbAGpkBGAoQOq2w8sz6qtjpw-r8O9uqT30,OUT_OF_NETWORK,O045?_ntb=%2Fb3tu0iwTKeaQVASZGH%2F8w%3D%3D",
    "location": "Greater Birmingham, Alabama Area",
    "name": "Ashley Allen",
    "photo": "https://media.licdn.com/dms/image/C5103AQEIbZbI9fkCuw/profile-displayphoto-shrink_100_100/0/1516971543261?e=1714608000&v=beta&t=cf62TZEr1ecff5jgVs5rnxuyBSM5oFP_U-BxFtVLOh8",
    "title": "Buyer"
  },
  {
    "about": "",
    "company": "Wilkins RV",
    "jobTitle": "3 years 3 months in role                    12 years 8 months in company",
    "leadPanel": "/sales/lead/ACwAAAlmLC4BcYm6snco4u2YuMawWdB7ZL0L6x8,NAME_SEARCH,_29A?_ntb=%2Fb3tu0iwTKeaQVASZGH%2F8w%3D%3D",
    "location": "Caledonia, New York, United States",
    "name": "John Miller",
    "photo": null,
    "title": "Used RV Purchaser"
  },
  {
    "about": "",
    "company": "Venture Metals +",
    "jobTitle": "3 years 2 months in role                    3 years 2 months in company",
    "leadPanel": "/sales/lead/ACwAADNfascBD_ZnfLORGUnaf4bhYXS5kAUksvc,NAME_SEARCH,XviU?_ntb=%2Fb3tu0iwTKeaQVASZGH%2F8w%3D%3D",
    "location": "Dallas-Fort Worth Metroplex",
    "name": "Justin Daniel",
    "photo": "https://media.licdn.com/dms/image/D5603AQH4mVNXHxK-1Q/profile-displayphoto-shrink_100_100/0/1700449964768?e=1714608000&v=beta&t=iVRGFF7tlbF-ygndZM_peO1o4mlEsykkgDKE7SmXBHo",
    "title": "Buyer"
  },
  {
    "about": "About:        see more",
    "company": "Buffalo Exchange",
    "jobTitle": "7 months in role                     7 months in company",
    "leadPanel": "/sales/lead/ACwAADQCHvcBLg_9Zmpz8vjFyr9VqLR25q3Av2U,OUT_OF_NETWORK,mMxe?_ntb=%2Fb3tu0iwTKeaQVASZGH%2F8w%3D%3D",
    "location": "New York, New York, United States",
    "name": "Alex Nilsson",
    "photo": null,
    "title": "Entry-level Buyer"
  },
  {
    "about": "",
    "company": "Safeway",
    "jobTitle": "6 months in role                     6 months in company",
    "leadPanel": "/sales/lead/ACwAAAHc4usBuHZgLsM60BbAh2zJVUqIvB8sHD0,NAME_SEARCH,_RLc?_ntb=%2Fb3tu0iwTKeaQVASZGH%2F8w%3D%3D",
    "location": "St Louis, Missouri, United States",
    "name": "Sara Roe",
    "photo": "https://media.licdn.com/dms/image/D4E03AQHU4FBqf2LMWw/profile-displayphoto-shrink_100_100/0/1682098452956?e=1714608000&v=beta&t=KFDwpxEsZxnnPaAIpb2UaVNHtWTDaaXazz5RMjsPmLM",
    "title": "Buyer - Footwear & Branded Activewear"
  },
  {
    "about": "",
    "company": "Rural King",
    "jobTitle": "22 years 5 months in role                    22 years 5 months in company",
    "leadPanel": "/sales/lead/ACwAABIN90IBf0GkM5jyYFCCntFp-BZ5gzDfHwM,NAME_SEARCH,Hs1K?_ntb=%2Fb3tu0iwTKeaQVASZGH%2F8w%3D%3D",
    "location": "United States",
    "name": "christina rutz",
    "photo": null,
    "title": "sales estate buyer"
  },
  {
    "about": "",
    "company": "CarMax",
    "jobTitle": "9 months in role                     9 months in company",
    "leadPanel": "/sales/lead/ACwAABkgF5YBKfZrORQ6v7U1bSvoy2NKd7jhUlk,NAME_SEARCH,GBnQ?_ntb=%2Fb3tu0iwTKeaQVASZGH%2F8w%3D%3D",
    "location": "Greater Seattle Area",
    "name": "Mccall Wilson",
    "photo": "https://media.licdn.com/dms/image/C5603AQHwlF41Kqy1KA/profile-displayphoto-shrink_100_100/0/1517694145037?e=1714608000&v=beta&t=ss56q5QTtC_jYF9W8rxwFCioEpwTu_-MzUkBuAPYql4",
    "title": "Meat buyer"
  },
  {
    "about": "About:        see more",
    "company": "The TJX Companies, Inc.",
    "jobTitle": "3 months in role                    6 years 3 months in company",
    "leadPanel": "/sales/lead/ACwAADXDpK0BAmPV6UZIxcMI7rU1dN1E1oVEl9o,NAME_SEARCH,29oB?_ntb=%2Fb3tu0iwTKeaQVASZGH%2F8w%3D%3D",
    "location": "Mattoon, Illinois, United States",
    "name": "Chuck Peterson",
    "photo": null,
    "title": "Buyer"
  },
  {
    "about": "About:        see more",
    "company": "Be Home",
    "jobTitle": "1 year 2 months in role                    2 years 9 months in company",
    "leadPanel": "/sales/lead/ACwAACqUgX4BYSlxnFIbJo1bkbKRy7wIJHcbU_4,NAME_SEARCH,2Pqn?_ntb=%2Fb3tu0iwTKeaQVASZGH%2F8w%3D%3D",
    "location": "Hixson, Tennessee, United States",
    "name": "Jonathan Shea",
    "photo": "https://media.licdn.com/dms/image/C4E03AQGJya9F_DpIHw/profile-displayphoto-shrink_100_100/0/1516965700365?e=1714608000&v=beta&t=upcILp-frOS3F9wWRqhYxHKpfORwgT9ScP11fe3GkgE",
    "title": "Buyer"
  },
  {
    "about": "",
    "company": "JOANN Stores",
    "jobTitle": "4 years 3 months in role                    5 years 8 months in company",
    "leadPanel": "/sales/lead/ACwAACSgofgBdfCPxPQxhG9Y8EzQqBNRTZ7wH9U,NAME_SEARCH,I4q-?_ntb=%2Fb3tu0iwTKeaQVASZGH%2F8w%3D%3D",
    "location": "Providence County, Rhode Island, United States",
    "name": "Benjamin Canestrari",
    "photo": null,
    "title": "Buyer"
  },
  {
    "about": "About:        see more",
    "company": "Grocery Outlet",
    "jobTitle": "2 years 5 months in role                    2 years 5 months in company",
    "leadPanel": "/sales/lead/ACwAAAunxuMBNjqRpDVPU4z2VsCks4APNdIW9sQ,NAME_SEARCH,Gq_6?_ntb=%2Fb3tu0iwTKeaQVASZGH%2F8w%3D%3D",
    "location": "Daphne, Alabama, United States",
    "name": "Eric Sparks",
    "photo": "https://media.licdn.com/dms/image/C5603AQHH-qCzObzHiw/profile-displayphoto-shrink_100_100/0/1516887955741?e=1714608000&v=beta&t=VsljC57HX6DDRNy1O823Rg8vHaRk5oIkdWbcAXkR6Fc",
    "title": "Menswear Buyer at CK Collection"
  },
  {
    "about": "",
    "company": "",
    "jobTitle": "2 years 6 months in role                    2 years 6 months in company",
    "leadPanel": "/sales/lead/ACwAAA0umC0BqjRRlunK2fv6VdzkUfrHP72jzLs,NAME_SEARCH,gh33?_ntb=%2Fb3tu0iwTKeaQVASZGH%2F8w%3D%3D",
    "location": "San Francisco, California, United States",
    "name": "Jacqueline Arko",
    "photo": null,
    "title": "Buyer Ecom"
  },
  {
    "about": "",
    "company": "",
    "jobTitle": "5 years 5 months in role                    16 years 7 months in company",
    "leadPanel": "/sales/lead/ACwAAAIpa5oBHVLtnbW5dozXUm3H8IEd8g1uy_E,NAME_SEARCH,-fsR?_ntb=%2Fb3tu0iwTKeaQVASZGH%2F8w%3D%3D",
    "location": "Greater Cleveland",
    "name": "Sarah Scroggy",
    "photo": "https://media.licdn.com/dms/image/D5603AQFk9ezQLO-r6A/profile-displayphoto-shrink_100_100/0/1662008779997?e=1714608000&v=beta&t=5ukCp5MTAfeF47SmAdCKLU79Wyok_fGQ6obvTTDowR0",
    "title": "Buyer"
  },
  {
    "about": "About:        see more",
    "company": "",
    "jobTitle": "3 months in role                    4 years 1 month in company",
    "leadPanel": "/sales/lead/ACwAAAGlNO8BhH6dPenI4DdGPbOLqH1RVneGy1w,NAME_SEARCH,mx7V?_ntb=%2Fb3tu0iwTKeaQVASZGH%2F8w%3D%3D",
    "location": "San Francisco Bay Area",
    "name": "Tonya Rice",
    "photo": null,
    "title": "Buyer Frozen Ice Cream/Desserts, Vegetables and Fruit"
  },
  {
    "about": "",
    "company": "Ollie's Bargain Outlet - Harrisburg, PA",
    "jobTitle": "7 years 7 months in role                    7 years 7 months in company",
    "leadPanel": "/sales/lead/ACwAAAK2sgwBenVtkMW991y2dDajFJsD1h7FIKQ,NAME_SEARCH,H0FD?_ntb=%2Fb3tu0iwTKeaQVASZGH%2F8w%3D%3D",
    "location": "Carlisle, Pennsylvania, United States",
    "name": "Ken Smith",
    "photo": "https://media.licdn.com/dms/image/D4E03AQHU4FBqf2LMWw/profile-displayphoto-shrink_100_100/0/1682098452956?e=1714608000&v=beta&t=KFDwpxEsZxnnPaAIpb2UaVNHtWTDaaXazz5RMjsPmLM",
    "title": "Buyer"
  },
  {
    "about": "",
    "company": "Uline",
    "jobTitle": "4 years 2 months in role                    4 years 2 months in company",
    "leadPanel": "/sales/lead/ACwAAAD-YWIBK1_3IshnSEIUcK_ZuDAN6Qaw8Og,NAME_SEARCH,1bbk?_ntb=%2Fb3tu0iwTKeaQVASZGH%2F8w%3D%3D",
    "location": "Greater Chicago Area",
    "name": "Patrick Hink",
    "photo": null,
    "title": "Branch Buyer"
  },
  {
    "about": "",
    "company": "The TJX Companies, Inc.",
    "jobTitle": "2 years 6 months in role                    6 years 10 months in company",
    "leadPanel": "/sales/lead/ACwAAAzoMVIBeFkaGcttbAg1RlnvA4e-6FviRTE,NAME_SEARCH,8T2V?_ntb=%2Fb3tu0iwTKeaQVASZGH%2F8w%3D%3D",
    "location": "Greater Boston",
    "name": "Kevin Seifert",
    "photo": "data:image/gif;base64,R0lGODlhAQABAIAAAAAAAP///yH5BAEAAAAALAAAAAABAAEAAAIBRAA7",
    "title": "Buyer"
  },
  {
    "about": "",
    "company": "Ben Bridge Jeweler",
    "jobTitle": "6 years 1 month in role                    30 years 8 months in company",
    "leadPanel": "/sales/lead/ACwAAAcQxGMBz3MdZ8IRfbn_wJio4jPFTRQSjcM,NAME_SEARCH,X848?_ntb=%2Fb3tu0iwTKeaQVASZGH%2F8w%3D%3D",
    "location": "Greater Seattle Area",
    "name": "Joe Perez CGA (AGS)",
    "photo": null,
    "title": "Watch Buyer"
  },
  {
    "about": "",
    "company": "Wacker Neuson SE",
    "jobTitle": "5 years 3 months in role                    5 years 3 months in company",
    "leadPanel": "/sales/lead/ACwAAAW0TRoBETYt6XrAWFpD4A900cd9twMm8KE,NAME_SEARCH,DRip?_ntb=%2Fb3tu0iwTKeaQVASZGH%2F8w%3D%3D",
    "location": "Menomonee Falls, Wisconsin, United States",
    "name": "Bobby Salm",
    "photo": "https://media.licdn.com/dms/image/C4E03AQEirhRHRSx9TQ/profile-displayphoto-shrink_100_100/0/1517754665801?e=1714608000&v=beta&t=G5aDx3Zg-TrporoREoQkTQam39MX-BV-6NbB5hP-ktw",
    "title": "Buyer/Planner"
  },
  {
    "about": "",
    "company": "Bayview Farm & Garden",
    "jobTitle": "5 years 2 months in role                    5 years 2 months in company",
    "leadPanel": "/sales/lead/ACwAAB0jaq0Bgqhb7YrEjt4Lyla5YEIpGQ0d6X4,NAME_SEARCH,THql?_ntb=%2Fb3tu0iwTKeaQVASZGH%2F8w%3D%3D",
    "location": "Greater Seattle Area",
    "name": "Gordon C. White",
    "photo": null,
    "title": "Nursery Buyer and Manager"
  },
  {
    "about": "",
    "company": "Publix Super Markets",
    "jobTitle": "3 years 4 months in role                    7 years 2 months in company",
    "leadPanel": "/sales/lead/ACwAABk6mJoBWxH9ZRz6m5SYEKQdrotQV77qQbY,NAME_SEARCH,ObAu?_ntb=%2Fb3tu0iwTKeaQVASZGH%2F8w%3D%3D",
    "location": "Greater Tampa Bay Area",
    "name": "Ryan Calcutti",
    "photo": "https://media.licdn.com/dms/image/C4D03AQGKrNIZMMzqiQ/profile-displayphoto-shrink_200_200/0/1601321723094?e=1714608000&v=beta&t=aSYyUi5uuhPrDVOTXNFm4dEzAa-mdRwzDpcw3ZBoUYc",
    "title": "Buyer"
  },
  {
    "about": "",
    "company": "Peterson Sheet Metal, Inc.",
    "jobTitle": "2 years 8 months in role                    2 years 8 months in company",
    "leadPanel": "/sales/lead/ACwAAAe1qLQBNW6zFlBSLn6Djvr8sClR7Evcshw,NAME_SEARCH,enLE?_ntb=%2Fb3tu0iwTKeaQVASZGH%2F8w%3D%3D",
    "location": "Minneapolis, Minnesota, United States",
    "name": "Eric Vilendrer",
    "photo": null,
    "title": "Purchaser"
  },
  {
    "about": "About:        see more",
    "company": "Ag Express Electronics Inc",
    "jobTitle": "1 year 3 months in role                    3 years 1 month in company",
    "leadPanel": "/sales/lead/ACwAAB-G0gcBNQxP1xMmpF9h9ZepXcgEMP4suQY,NAME_SEARCH,GpIO?_ntb=%2Fb3tu0iwTKeaQVASZGH%2F8w%3D%3D",
    "location": "Monroe, Iowa, United States",
    "name": "Cortney Price",
    "photo": "https://media.licdn.com/dms/image/C5603AQHZNpJCLNPXlw/profile-displayphoto-shrink_100_100/0/1566768465610?e=1714608000&v=beta&t=cRmvmQ3QsokdYlWpFoQVuao6LX8ziHSyQtysAj1C0-Y",
    "title": "Purchaser"
  },
  {
    "about": "About:        see more",
    "company": "Nordstrom",
    "jobTitle": "2 years 9 months in role                    14 years 11 months in company",
    "leadPanel": "/sales/lead/ACwAAA12eOcB2KGfDoT6tDQ7gg2DWiWAjMYSm-s,NAME_SEARCH,dlQF?_ntb=%2Fb3tu0iwTKeaQVASZGH%2F8w%3D%3D",
    "location": "Seattle, Washington, United States",
    "name": "Austin Mumford (he/him)",
    "photo": null,
    "title": "Buyer, Associate - Mens Active Apparel"
  },
  {
    "about": "About:        see more",
    "company": "CosmoProf Beauty",
    "jobTitle": "1 year  in role                    3 years  in company",
    "leadPanel": "/sales/lead/ACwAABfym0MBv60A7_bD1u0t_i-GIanpWW__4uo,NAME_SEARCH,VcJH?_ntb=%2Fb3tu0iwTKeaQVASZGH%2F8w%3D%3D",
    "location": "Dallas, Texas, United States",
    "name": "Victoria Scholten",
    "photo": "https://media.licdn.com/dms/image/D4E03AQHU4FBqf2LMWw/profile-displayphoto-shrink_100_100/0/1682098452956?e=1714608000&v=beta&t=KFDwpxEsZxnnPaAIpb2UaVNHtWTDaaXazz5RMjsPmLM",
    "title": "Buyer - Hair Care"
  },
  {
    "about": "",
    "company": "The TJX Companies, Inc.",
    "jobTitle": "4 years 2 months in role                    8 years 3 months in company",
    "leadPanel": "/sales/lead/ACwAAApZH7IBv_GLrKPv--jfMKeB8MNPYDdZK9Q,NAME_SEARCH,2V_J?_ntb=%2Fb3tu0iwTKeaQVASZGH%2F8w%3D%3D",
    "location": "Boston, Massachusetts, United States",
    "name": "Mariah Leven",
    "photo": null,
    "title": "Buyer"
  },
  {
    "about": "",
    "company": "Ross Stores, Inc.",
    "jobTitle": "3 years 2 months in role                    7 years 11 months in company",
    "leadPanel": "/sales/lead/ACwAAAu4uEcBYwWxLzrIZpJxwNO_kUFFzWHSy9Y,NAME_SEARCH,faoP?_ntb=%2Fb3tu0iwTKeaQVASZGH%2F8w%3D%3D",
    "location": "New York City Metropolitan Area",
    "name": "Stephanie Abrams",
    "photo": "https://media.licdn.com/dms/image/D5603AQGNMkbqxaCQDw/profile-displayphoto-shrink_100_100/0/1700325806692?e=1714608000&v=beta&t=ZsmNFh7mJ4wGoopCAPoAVIip9Q7QjuD3d7R1ViN-1_k",
    "title": "Buyer"
  },
  {
    "about": "About:        see more",
    "company": "Stop & Shop",
    "jobTitle": "6 years 6 months in role                    6 years 6 months in company",
    "leadPanel": "/sales/lead/ACwAAAZyph4Bty7nS9Q9TmkozEu6cANn-FBkEnM,NAME_SEARCH,GRyA?_ntb=%2Fb3tu0iwTKeaQVASZGH%2F8w%3D%3D",
    "location": "Greater Boston",
    "name": "Joel Kaplan",
    "photo": null,
    "title": "Produce Buyer lll"
  },
  {
    "about": "About:        see more",
    "company": "Firstbase",
    "jobTitle": "2 years 1 month in role                    2 years 1 month in company",
    "leadPanel": "/sales/lead/ACwAACvKarYBN3LdIEl6589Y4whrMr9Plw9ug64,NAME_SEARCH,ZiVt?_ntb=%2Fb3tu0iwTKeaQVASZGH%2F8w%3D%3D",
    "location": "Atlanta, Georgia, United States",
    "name": "Amy Smith",
    "photo": "https://media.licdn.com/dms/image/D4E03AQH9Tn7vhMixmQ/profile-displayphoto-shrink_100_100/0/1683330313632?e=1714608000&v=beta&t=U-qL4a5hv6B93ApbsFTqtK7XVDWdQTwxHR6Z19yUW1E",
    "title": "Buyer"
  },
  {
    "about": "About:        see more",
    "company": "American Water",
    "jobTitle": "10 years 9 months in role                    10 years 9 months in company",
    "leadPanel": "/sales/lead/ACwAAAGxrqYBMQe2fxKtRLorBof_QGDFkSbV93g,NAME_SEARCH,zSVa?_ntb=%2Fb3tu0iwTKeaQVASZGH%2F8w%3D%3D",
    "location": "St Charles, Illinois, United States",
    "name": "Bill Crow",
    "photo": null,
    "title": "Buyer"
  },
  {
    "about": "",
    "company": "The TJX Companies, Inc.",
    "jobTitle": "16 years  in role                    16 years  in company",
    "leadPanel": "/sales/lead/ACwAAAF91zsBesLRS114jzEGRLz4UBHv20qU5s4,NAME_SEARCH,-tp-?_ntb=%2Fb3tu0iwTKeaQVASZGH%2F8w%3D%3D",
    "location": "Waco, Texas, United States",
    "name": "Sheree Haddix",
    "photo": "https://media.licdn.com/dms/image/C4D03AQGdkMlFlqLQSg/profile-displayphoto-shrink_100_100/0/1629257135412?e=1714608000&v=beta&t=7hjeUwCDrl31ZPmsdB6DDuBozOPQF7x-GTd5WNIRlhw",
    "title": "Buyer Decorative Accents HomeSense"
  },
  {
    "about": "",
    "company": "Shurtape Technologies, LLC",
    "jobTitle": "1 year 2 months in role                    1 year 2 months in company",
    "leadPanel": "/sales/lead/ACwAAB_m3X0Bhy9t7XRqNdOu2l9H3UboUtngqq0,NAME_SEARCH,UW1O?_ntb=%2Fb3tu0iwTKeaQVASZGH%2F8w%3D%3D",
    "location": "Cleveland, Ohio, United States",
    "name": "Emily Lyons-Glashauser",
    "photo": null,
    "title": "Buyer"
  },
  {
    "about": "About:        see more",
    "company": "Marine Corps Community Services",
    "jobTitle": "6 years 6 months in role                    6 years 6 months in company",
    "leadPanel": "/sales/lead/ACwAAAKvDwYBmICaEcvLsp1T0ZgRovf6q5LpsXc,NAME_SEARCH,lJAv?_ntb=%2Fb3tu0iwTKeaQVASZGH%2F8w%3D%3D",
    "location": "New York City Metropolitan Area",
    "name": "Angeleque V.",
    "photo": "https://media.licdn.com/dms/image/C5603AQE2BV-NcLvq_w/profile-displayphoto-shrink_100_100/0/1516443503392?e=1714608000&v=beta&t=ySQZDOKEChgXyaUPpWGmr_n2LsSTD8Tsp9K0T-a36ds",
    "title": "Buyer: Ladies', Men's and Children's Footwear"
  },
  {
    "about": "",
    "company": "Universal Destinations & Experiences",
    "jobTitle": "2 years 8 months in role                    2 years 8 months in company",
    "leadPanel": "/sales/lead/ACwAABAeLT4BK1eXGoyGuDaKdzb0lHD7_lEQr0M,NAME_SEARCH,7Vob?_ntb=%2Fb3tu0iwTKeaQVASZGH%2F8w%3D%3D",
    "location": "Clermont, Florida, United States",
    "name": "Kaylynn Whitley",
    "photo": null,
    "title": "Consignment Buyer/ Area Merchandiser"
  }
]